{"success":true,"code":2000,"message":"后台处理成功","result":{"earlyWarningStatus":null,"appSchoolPhotoInfoEntityList":[{"id":36369,"createTime":"2022-06-23 14:03:03","updateTime":null,"createUser":"admin","updateUser":null,"active":true,"schoolName":"杭州市江心岛小学（北校区）","year":"2022","thumbnailUrl":"https://rxyj.hzedu.gov.cn/hzjyFile/school/2022-05-20/33f8ecdf-dd84-42a3-9862-28ce2a7858b625.jpg","orderBy":1,"xqbsm":"2133002592001"},{"id":36370,"createTime":"2022-06-23 14:03:03","updateTime":null,"createUser":"admin","updateUser":null,"active":true,"schoolName":"杭州市江心岛小学（北校区）","year":"2022","thumbnailUrl":"https://rxyj.hzedu.gov.cn/hzjyFile/school/2022-05-20/23612875-e25f-465b-998c-20ab4619736a22.jpg","orderBy":1,"xqbsm":"2133002592001"},{"id":36371,"createTime":"2022-06-23 14:03:03","updateTime":null,"createUser":"admin","updateUser":null,"active":true,"schoolName":"杭州市江心岛小学（北校区）","year":"2022","thumbnailUrl":"https://rxyj.hzedu.gov.cn/hzjyFile/school/2022-05-20/76e9a75c-d84f-4740-b6c7-7226cb91575724.jpg","orderBy":1,"xqbsm":"2133002592001"},{"id":36372,"createTime":"2022-06-23 14:03:03","updateTime":null,"createUser":"admin","updateUser":null,"active":true,"schoolName":"杭州市江心岛小学（北校区）","year":"2022","thumbnailUrl":"https://rxyj.hzedu.gov.cn/hzjyFile/school/2022-05-20/a12dcbd9-0c89-42f7-936b-61fba54bdffe23.jpg","orderBy":1,"xqbsm":"2133002592001"}],"mapInfoEntities":null,"appSchoolDistrictInfoEntityList":[{"id":20287,"createTime":"2022-06-23 14:03:03","updateTime":null,"createUser":"admin","updateUser":null,"active":true,"qxmc":"杭州市拱墅区","year":"2022","schoolName":"杭州市江心岛小学（北校区）","xqbsm":"2133002592001","jdmc":"朝晖街道","sqmc":"塘南社区","name":"朝晖七区","streetCode":"330105016","streetName":"朝晖街道","communityCode":"330105016008000","communityName":"塘南社区","xqbm":"3500011054","xqmc":"朝晖七区","buildingNumber":null,"buildingNumberZh":null,"xqId":"20287","fwsm":null,"dw":null,"bak1":"否","lzhZh":null,"isShow":"1","bak2":"户籍生","gajSchoolAddressEntities":null,"hjsrs":null,"jtthrs":null,"jthrs":null,"ybsrs":null,"hjsqrrs":null,"jtthqrrs":null,"jthqrrs":null,"ybsqrrs":null},{"id":26020,"createTime":"2022-06-23 14:03:03","updateTime":null,"createUser":"admin","updateUser":null,"active":true,"qxmc":"杭州市拱墅区","year":"2022","schoolName":"杭州市江心岛小学（北校区）","xqbsm":"2133002592001","jdmc":"朝晖街道","sqmc":"虹园社区","name":"朝晖九区","streetCode":"330105016","streetName":"朝晖街道","communityCode":"330105016010000","communityName":"虹园社区","xqbm":"3700011088","xqmc":"朝晖九区","buildingNumber":null,"buildingNumberZh":null,"xqId":"26020","fwsm":null,"dw":null,"bak1":"否","lzhZh":null,"isShow":"1","bak2":"户籍生","gajSchoolAddressEntities":null,"hjsrs":null,"jtthrs":null,"jthrs":null,"ybsrs":null,"hjsqrrs":null,"jtthqrrs":null,"jthqrrs":null,"ybsqrrs":null},{"id":25112,"createTime":"2022-06-23 14:03:03","updateTime":null,"createUser":"admin","updateUser":null,"active":true,"qxmc":"杭州市拱墅区","year":"2022","schoolName":"杭州市江心岛小学（北校区）","xqbsm":"2133002592001","jdmc":"朝晖街道","sqmc":"稻香园社区","name":"稻香园","streetCode":"330105016","streetName":"朝晖街道","communityCode":"330105016011000","communityName":"稻香园社区","xqbm":"3800011085","xqmc":"稻香园","buildingNumber":null,"buildingNumberZh":null,"xqId":"25112","fwsm":null,"dw":null,"bak1":"否","lzhZh":null,"isShow":"1","bak2":"户籍生","gajSchoolAddressEntities":null,"hjsrs":null,"jtthrs":null,"jthrs":null,"ybsrs":null,"hjsqrrs":null,"jtthqrrs":null,"jthqrrs":null,"ybsqrrs":null},{"id":23895,"createTime":"2022-06-23 14:03:03","updateTime":null,"createUser":"admin","updateUser":null,"active":true,"qxmc":"杭州市拱墅区","year":"2022","schoolName":"杭州市江心岛小学（北校区）","xqbsm":"2133002592001","jdmc":"朝晖街道","sqmc":"河东社区","name":"黎明园","streetCode":"330105016","streetName":"朝晖街道","communityCode":"330105016009000","communityName":"河东社区","xqbm":"0900011083","xqmc":"黎明园","buildingNumber":null,"buildingNumberZh":null,"xqId":"23895","fwsm":null,"dw":null,"bak1":"否","lzhZh":null,"isShow":"1","bak2":"户籍生","gajSchoolAddressEntities":null,"hjsrs":null,"jtthrs":null,"jthrs":null,"ybsrs":null,"hjsqrrs":null,"jtthqrrs":null,"jthqrrs":null,"ybsqrrs":null},{"id":20286,"createTime":"2022-06-23 14:03:03","updateTime":null,"createUser":"admin","updateUser":null,"active":true,"qxmc":"杭州市拱墅区","year":"2022","schoolName":"杭州市江心岛小学（北校区）","xqbsm":"2133002592001","jdmc":"朝晖街道","sqmc":"塘南社区","name":"庆晖公寓","streetCode":"330105016","streetName":"朝晖街道","communityCode":"330105016008000","communityName":"塘南社区","xqbm":"3500011053","xqmc":"庆晖公寓","buildingNumber":null,"buildingNumberZh":null,"xqId":"20286","fwsm":null,"dw":null,"bak1":"否","lzhZh":null,"isShow":"1","bak2":"户籍生","gajSchoolAddressEntities":null,"hjsrs":null,"jtthrs":null,"jthrs":null,"ybsrs":null,"hjsqrrs":null,"jtthqrrs":null,"jthqrrs":null,"ybsqrrs":null},{"id":26019,"createTime":"2022-06-23 14:03:03","updateTime":null,"createUser":"admin","updateUser":null,"active":true,"qxmc":"杭州市拱墅区","year":"2022","schoolName":"杭州市江心岛小学（北校区）","xqbsm":"2133002592001","jdmc":"朝晖街道","sqmc":"虹园社区","name":"天盛居","streetCode":"330105016","streetName":"朝晖街道","communityCode":"330105016010000","communityName":"虹园社区","xqbm":"3700011087","xqmc":"天盛居","buildingNumber":null,"buildingNumberZh":null,"xqId":"26019","fwsm":null,"dw":null,"bak1":"否","lzhZh":null,"isShow":"1","bak2":"户籍生","gajSchoolAddressEntities":null,"hjsrs":null,"jtthrs":null,"jthrs":null,"ybsrs":null,"hjsqrrs":null,"jtthqrrs":null,"jthqrrs":null,"ybsqrrs":null},{"id":23892,"createTime":"2022-06-23 14:03:03","updateTime":null,"createUser":"admin","updateUser":null,"active":true,"qxmc":"杭州市拱墅区","year":"2022","schoolName":"杭州市江心岛小学（北校区）","xqbsm":"2133002592001","jdmc":"朝晖街道","sqmc":"河东社区","name":"文晖园","streetCode":"330105016","streetName":"朝晖街道","communityCode":"330105016009000","communityName":"河东社区","xqbm":"0900011080","xqmc":"文晖园","buildingNumber":null,"buildingNumberZh":null,"xqId":"23892","fwsm":null,"dw":null,"bak1":"否","lzhZh":null,"isShow":"1","bak2":"户籍生","gajSchoolAddressEntities":null,"hjsrs":null,"jtthrs":null,"jthrs":null,"ybsrs":null,"hjsqrrs":null,"jtthqrrs":null,"jthqrrs":null,"ybsqrrs":null},{"id":23893,"createTime":"2022-06-23 14:03:03","updateTime":null,"createUser":"admin","updateUser":null,"active":true,"qxmc":"杭州市拱墅区","year":"2022","schoolName":"杭州市江心岛小学（北校区）","xqbsm":"2133002592001","jdmc":"朝晖街道","sqmc":"河东社区","name":"武林外滩公寓","streetCode":"330105016","streetName":"朝晖街道","communityCode":"330105016009000","communityName":"河东社区","xqbm":"0900011081","xqmc":"武林外滩公寓","buildingNumber":null,"buildingNumberZh":null,"xqId":"23893","fwsm":null,"dw":null,"bak1":"否","lzhZh":null,"isShow":"1","bak2":"户籍生","gajSchoolAddressEntities":null,"hjsrs":null,"jtthrs":null,"jthrs":null,"ybsrs":null,"hjsqrrs":null,"jtthqrrs":null,"jthqrrs":null,"ybsqrrs":null}],"appSchoolClassEntityList":[],"appSchoolInfoEntity":{"id":11491,"createTime":"2021-09-03 14:32:29","updateTime":"2022-06-23 14:03:03","createUser":null,"updateUser":"admin","active":true,"year":"2022","schoolCode":"2133002592","schoolName":"杭州市江心岛小学（北校区）","schoolType":"2","gmblx":"非民办","schoolOtherName":null,"address":"杭州市拱墅区古河巷72号","phoneNumber":null,"schoolWay":"红石板新村公交站下车，沿古河巷往北走。","recruitType":"户籍生","recruitCount":0,"registerCount":0,"sqznrs":0,"xssqrs":0,"shuntBd":null,"shuntWd":null,"schoolDetail":"杭州市江心岛小学创建于1998年，目前分年级实施两校区办学，学校规划合理，教学设施齐全。学校坚持“全纳优质”“融合共生”的办学理念，致力于深化课程与教学改革，强化学科教育基础，发挥“三心一体化”的管理优势，提高教育教学质量，提升学校办学品位，目前是区域内具有鲜明办学特色的小班化教育学校。","highTeacher":0,"middleTeacher":0,"primaryTeacher":0,"workerNumber":77,"shzt":2,"shztbz":"","absentNumber":77,"authorizedNumber":0,"schoolHonor":null,"enrollFileName":null,"enrollFileUrl":null,"zsjzxs":null,"enrollFileNameMid":null,"enrollFileUrlMid":null,"zsjzxsMid":null,"schoolFeature":null,"schoolMotto":null,"campusDistribution":null,"directPrimarySchoolCode":null,"directPrimarySchoolName":null,"directMiddleSchoolCode":null,"directMiddleSchoolName":"杭州市朝晖中学","warningLevel":null,"warningYear":null,"warningPercent":null,"publishStatus":null,"yjfbzt":"2","bdIsshunt1":null,"bdShunt1":null,"wdIsshunt1":"1","wdShunt1":null,"bdIsshunt2":null,"bdShunt2":null,"wdIsshunt2":"1","wdShunt2":"false","bdIsshunt3":null,"bdShunt3":null,"wdIsshunt3":"1","wdShunt3":null,"schoolLogo":"https://rxyj.hzedu.gov.cn/hzjyFile/school/2022-05-20/260d427d-b2ed-4c85-a029-b7d4a0f6c0fe21.jpg","schoolScope":"稻香园社区、虹园社区、塘南社区适龄儿童和河东社区部分（文晖路以北）适龄儿童。","schoolScopeMid":null,"schoolTel":"0571—56317163","schoolmasterName":null,"dkczbz":null,"schoolmasterDesc":null,"visitTimes":828,"publishWarningDate":null,"lng":"120.159622","lat":"30.294035","dkczbsm":"3133002467001","splitFlowNum1":null,"splitFlowNum2":null,"splitFlowNum3":null,"seniorTeacherNum":0,"buildingAreaNum":10599,"hideFlag":"true","otherProvShunt1":"2","otherProvShunt1Mid":null,"otherProvShunt2":"2","otherProvShunt3":"2","otherSplitFlowNum1":null,"otherSplitFlowNum2":null,"otherSplitFlowNum3":null,"forecastClassNum1":4,"forecastClassNum2":4,"forecastClassNum3":4,"forecastClassPerson1":45,"forecastClassPerson2":45,"forecastClassPerson3":45,"forecastClassNum1Mid":0,"forecastClassNum2Mid":0,"forecastClassNum3Mid":0,"forecastClassPerson1Mid":0,"forecastClassPerson2Mid":0,"forecastClassPerson3Mid":0,"localShunt1":"2","localShunt1Mid":null,"localShunt2":"2","localShunt3":"2","oneSuper1":"","oneSuper1Mid":null,"oneSuper2":"","oneSuper3":"","oneSuperTime1":"","oneSuperTime1Mid":null,"oneSuperTime2":"","oneSuperTime3":"","classTotalNum":27,"gradeTotalNum":0,"schoolAreaNum":19334,"gmblxSort":0,"generalSchoolName":null,"generalSchoolFlag":null,"visitCount":null,"szqmc":"下城区","szqdm":"330103000000","key1":"4","xqbsm":"2133002592001","xxmc":"杭州市江心岛小学","xqmc":"北校区","xsrs":862,"recruitTypeNewhzr":null,"schoolScopeNewhzr":null,"distnum":null,"disttime":null,"wdIsshunt1Mid":null,"wdIsshunt2Mid":null,"wdIsshunt3Mid":null,"publishStatusMid":"0","xqdt":null,"showSchoolName":"杭州市江心岛小学","appXcFlag":"0"},"appSchoolTypeInfoVOList":[{"id":11491,"createTime":null,"updateTime":null,"schoolType":"2","sqznrs":0,"xssqrs":0}],"appSchoolDistrictInfoEntityListNewHZR":[{"id":20286,"createTime":"2022-06-23 14:03:03","updateTime":null,"createUser":"admin","updateUser":null,"active":true,"qxmc":null,"year":"2022","schoolName":"杭州市江心岛小学（北校区）","xqbsm":"2133002592001","jdmc":"朝晖街道","sqmc":"塘南社区","name":"庆晖公寓","streetCode":"330105016","streetName":"朝晖街道","communityCode":"330105016008000","communityName":"塘南社区","xqbm":"3500011053","xqmc":"庆晖公寓","buildingNumber":null,"buildingNumberZh":null,"xqId":"20286","fwsm":null,"dw":null,"bak1":"否","lzhZh":null,"isShow":"1","bak2":"新杭州人","gajSchoolAddressEntities":null,"hjsrs":null,"jtthrs":null,"jthrs":null,"ybsrs":null,"hjsqrrs":null,"jtthqrrs":null,"jthqrrs":null,"ybsqrrs":null},{"id":20287,"createTime":"2022-06-23 14:03:03","updateTime":null,"createUser":"admin","updateUser":null,"active":true,"qxmc":null,"year":"2022","schoolName":"杭州市江心岛小学（北校区）","xqbsm":"2133002592001","jdmc":"朝晖街道","sqmc":"塘南社区","name":"朝晖七区","streetCode":"330105016","streetName":"朝晖街道","communityCode":"330105016008000","communityName":"塘南社区","xqbm":"3500011054","xqmc":"朝晖七区","buildingNumber":null,"buildingNumberZh":null,"xqId":"20287","fwsm":null,"dw":null,"bak1":"否","lzhZh":null,"isShow":"1","bak2":"新杭州人","gajSchoolAddressEntities":null,"hjsrs":null,"jtthrs":null,"jthrs":null,"ybsrs":null,"hjsqrrs":null,"jtthqrrs":null,"jthqrrs":null,"ybsqrrs":null},{"id":23892,"createTime":"2022-06-23 14:03:03","updateTime":null,"createUser":"admin","updateUser":null,"active":true,"qxmc":null,"year":"2022","schoolName":"杭州市江心岛小学（北校区）","xqbsm":"2133002592001","jdmc":"朝晖街道","sqmc":"河东社区","name":"文晖园","streetCode":"330105016","streetName":"朝晖街道","communityCode":"330105016009000","communityName":"河东社区","xqbm":"0900011080","xqmc":"文晖园","buildingNumber":null,"buildingNumberZh":null,"xqId":"23892","fwsm":null,"dw":null,"bak1":"否","lzhZh":null,"isShow":"1","bak2":"新杭州人","gajSchoolAddressEntities":null,"hjsrs":null,"jtthrs":null,"jthrs":null,"ybsrs":null,"hjsqrrs":null,"jtthqrrs":null,"jthqrrs":null,"ybsqrrs":null},{"id":23895,"createTime":"2022-06-23 14:03:03","updateTime":null,"createUser":"admin","updateUser":null,"active":true,"qxmc":null,"year":"2022","schoolName":"杭州市江心岛小学（北校区）","xqbsm":"2133002592001","jdmc":"朝晖街道","sqmc":"河东社区","name":"黎明园","streetCode":"330105016","streetName":"朝晖街道","communityCode":"330105016009000","communityName":"河东社区","xqbm":"0900011083","xqmc":"黎明园","buildingNumber":null,"buildingNumberZh":null,"xqId":"23895","fwsm":null,"dw":null,"bak1":"否","lzhZh":null,"isShow":"1","bak2":"新杭州人","gajSchoolAddressEntities":null,"hjsrs":null,"jtthrs":null,"jthrs":null,"ybsrs":null,"hjsqrrs":null,"jtthqrrs":null,"jthqrrs":null,"ybsqrrs":null},{"id":23893,"createTime":"2022-06-23 14:03:03","updateTime":null,"createUser":"admin","updateUser":null,"active":true,"qxmc":null,"year":"2022","schoolName":"杭州市江心岛小学（北校区）","xqbsm":"2133002592001","jdmc":"朝晖街道","sqmc":"河东社区","name":"武林外滩公寓","streetCode":"330105016","streetName":"朝晖街道","communityCode":"330105016009000","communityName":"河东社区","xqbm":"0900011081","xqmc":"武林外滩公寓","buildingNumber":null,"buildingNumberZh":null,"xqId":"23893","fwsm":null,"dw":null,"bak1":"否","lzhZh":null,"isShow":"1","bak2":"新杭州人","gajSchoolAddressEntities":null,"hjsrs":null,"jtthrs":null,"jthrs":null,"ybsrs":null,"hjsqrrs":null,"jtthqrrs":null,"jthqrrs":null,"ybsqrrs":null},{"id":26019,"createTime":"2022-06-23 14:03:03","updateTime":null,"createUser":"admin","updateUser":null,"active":true,"qxmc":null,"year":"2022","schoolName":"杭州市江心岛小学（北校区）","xqbsm":"2133002592001","jdmc":"朝晖街道","sqmc":"虹园社区","name":"天盛居","streetCode":"330105016","streetName":"朝晖街道","communityCode":"330105016010000","communityName":"虹园社区","xqbm":"3700011087","xqmc":"天盛居","buildingNumber":null,"buildingNumberZh":null,"xqId":"26019","fwsm":null,"dw":null,"bak1":"否","lzhZh":null,"isShow":"1","bak2":"新杭州人","gajSchoolAddressEntities":null,"hjsrs":null,"jtthrs":null,"jthrs":null,"ybsrs":null,"hjsqrrs":null,"jtthqrrs":null,"jthqrrs":null,"ybsqrrs":null},{"id":26020,"createTime":"2022-06-23 14:03:03","updateTime":null,"createUser":"admin","updateUser":null,"active":true,"qxmc":null,"year":"2022","schoolName":"杭州市江心岛小学（北校区）","xqbsm":"2133002592001","jdmc":"朝晖街道","sqmc":"虹园社区","name":"朝晖九区","streetCode":"330105016","streetName":"朝晖街道","communityCode":"330105016010000","communityName":"虹园社区","xqbm":"3700011088","xqmc":"朝晖九区","buildingNumber":null,"buildingNumberZh":null,"xqId":"26020","fwsm":null,"dw":null,"bak1":"否","lzhZh":null,"isShow":"1","bak2":"新杭州人","gajSchoolAddressEntities":null,"hjsrs":null,"jtthrs":null,"jthrs":null,"ybsrs":null,"hjsqrrs":null,"jtthqrrs":null,"jthqrrs":null,"ybsqrrs":null},{"id":25112,"createTime":"2022-06-23 14:03:03","updateTime":null,"createUser":"admin","updateUser":null,"active":true,"qxmc":null,"year":"2022","schoolName":"杭州市江心岛小学（北校区）","xqbsm":"2133002592001","jdmc":"朝晖街道","sqmc":"稻香园社区","name":"稻香园","streetCode":"330105016","streetName":"朝晖街道","communityCode":"330105016011000","communityName":"稻香园社区","xqbm":"3800011085","xqmc":"稻香园","buildingNumber":null,"buildingNumberZh":null,"xqId":"25112","fwsm":null,"dw":null,"bak1":"否","lzhZh":null,"isShow":"1","bak2":"新杭州人","gajSchoolAddressEntities":null,"hjsrs":null,"jtthrs":null,"jthrs":null,"ybsrs":null,"hjsqrrs":null,"jtthqrrs":null,"jthqrrs":null,"ybsqrrs":null},{"id":34043,"createTime":"2022-06-23 14:03:03","updateTime":null,"createUser":"admin","updateUser":null,"active":true,"qxmc":null,"year":"2022","schoolName":"杭州市江心岛小学（北校区）","xqbsm":"2133002592001","jdmc":"朝晖街道","sqmc":"河东社区","name":"文晖路","streetCode":"330105016","streetName":"朝晖街道","communityCode":"330105016009000","communityName":"河东社区","xqbm":"330105016009A0001","xqmc":"文晖路","buildingNumber":"３３６","buildingNumberZh":null,"xqId":"34043","fwsm":null,"dw":"号","bak1":"否","lzhZh":null,"isShow":"2","bak2":"新杭州人","gajSchoolAddressEntities":null,"hjsrs":null,"jtthrs":null,"jthrs":null,"ybsrs":null,"hjsqrrs":null,"jtthqrrs":null,"jthqrrs":null,"ybsqrrs":null}],"appSchoolMapInfoEntities":[{"id":22407,"createTime":"2022-06-23 14:03:03","updateTime":"2022-06-16 16:10:09","createUser":"admin","updateUser":null,"active":true,"year":"2022","xqbsm":"2133002592001","schoolName":"杭州市江心岛小学（北校区）","lng":"120.1648009276732","lat":"30.297277608170532","sequence":1,"bak1":null,"bak2":null,"bak3":null,"bak4":null,"bak5":null},{"id":22408,"createTime":"2022-06-23 14:03:03","updateTime":"2022-06-16 16:10:09","createUser":"admin","updateUser":null,"active":true,"year":"2022","xqbsm":"2133002592001","schoolName":"杭州市江心岛小学（北校区）","lng":"120.16014770513152","lat":"30.295671711882513","sequence":2,"bak1":null,"bak2":null,"bak3":null,"bak4":null,"bak5":null},{"id":22409,"createTime":"2022-06-23 14:03:03","updateTime":"2022-06-16 16:10:09","createUser":"admin","updateUser":null,"active":true,"year":"2022","xqbsm":"2133002592001","schoolName":"杭州市江心岛小学（北校区）","lng":"120.16233058752077","lat":"30.292693717398503","sequence":3,"bak1":null,"bak2":null,"bak3":null,"bak4":null,"bak5":null},{"id":22410,"createTime":"2022-06-23 14:03:03","updateTime":"2022-06-16 16:10:09","createUser":"admin","updateUser":null,"active":true,"year":"2022","xqbsm":"2133002592001","schoolName":"杭州市江心岛小学（北校区）","lng":"120.16700177617265","lat":"30.288951605310768","sequence":4,"bak1":null,"bak2":null,"bak3":null,"bak4":null,"bak5":null},{"id":22411,"createTime":"2022-06-23 14:03:03","updateTime":"2022-06-16 16:10:09","createUser":"admin","updateUser":null,"active":true,"year":"2022","xqbsm":"2133002592001","schoolName":"杭州市江心岛小学（北校区）","lng":"120.16563635179749","lat":"30.288826865757635","sequence":5,"bak1":null,"bak2":null,"bak3":null,"bak4":null,"bak5":null},{"id":22412,"createTime":"2022-06-23 14:03:03","updateTime":"2022-06-16 16:10:09","createUser":"admin","updateUser":null,"active":true,"year":"2022","xqbsm":"2133002592001","schoolName":"杭州市江心岛小学（北校区）","lng":"120.16159397700258","lat":"30.292568982652284","sequence":6,"bak1":null,"bak2":null,"bak3":null,"bak4":null,"bak5":null},{"id":22413,"createTime":"2022-06-23 14:03:03","updateTime":"2022-06-16 16:10:09","createUser":"admin","updateUser":null,"active":true,"year":"2022","xqbsm":"2133002592001","schoolName":"杭州市江心岛小学（北校区）","lng":"120.15967160321124","lat":"30.294954506901366","sequence":7,"bak1":null,"bak2":null,"bak3":null,"bak4":null,"bak5":null},{"id":22414,"createTime":"2022-06-23 14:03:03","updateTime":"2022-06-16 16:10:09","createUser":"admin","updateUser":null,"active":true,"year":"2022","xqbsm":"2133002592001","schoolName":"杭州市江心岛小学（北校区）","lng":"120.15925838267664","lat":"30.294673860031764","sequence":8,"bak1":null,"bak2":null,"bak3":null,"bak4":null,"bak5":null},{"id":22415,"createTime":"2022-06-23 14:03:03","updateTime":"2022-06-16 16:10:09","createUser":"admin","updateUser":null,"active":true,"year":"2022","xqbsm":"2133002592001","schoolName":"杭州市江心岛小学（北校区）","lng":"120.15927634878685","lat":"30.293255021773614","sequence":9,"bak1":null,"bak2":null,"bak3":null,"bak4":null,"bak5":null},{"id":22416,"createTime":"2022-06-23 14:03:03","updateTime":"2022-06-16 16:10:09","createUser":"admin","updateUser":null,"active":true,"year":"2022","xqbsm":"2133002592001","schoolName":"杭州市江心岛小学（北校区）","lng":"120.15999499319483","lat":"30.29182057080998","sequence":10,"bak1":null,"bak2":null,"bak3":null,"bak4":null,"bak5":null},{"id":22417,"createTime":"2022-06-23 14:03:03","updateTime":"2022-06-16 16:10:09","createUser":"admin","updateUser":null,"active":true,"year":"2022","xqbsm":"2133002592001","schoolName":"杭州市江心岛小学（北校区）","lng":"120.1611088920272","lat":"30.290542020568335","sequence":11,"bak1":null,"bak2":null,"bak3":null,"bak4":null,"bak5":null},{"id":22418,"createTime":"2022-06-23 14:03:03","updateTime":"2022-06-16 16:10:09","createUser":"admin","updateUser":null,"active":true,"year":"2022","xqbsm":"2133002592001","schoolName":"杭州市江心岛小学（北校区）","lng":"120.16238448585136","lat":"30.289450561921026","sequence":12,"bak1":null,"bak2":null,"bak3":null,"bak4":null,"bak5":null},{"id":22419,"createTime":"2022-06-23 14:03:03","updateTime":"2022-06-16 16:10:09","createUser":"admin","updateUser":null,"active":true,"year":"2022","xqbsm":"2133002592001","schoolName":"杭州市江心岛小学（北校区）","lng":"120.16233058752077","lat":"30.28871771851722","sequence":13,"bak1":null,"bak2":null,"bak3":null,"bak4":null,"bak5":null},{"id":22420,"createTime":"2022-06-23 14:03:03","updateTime":"2022-06-16 16:10:09","createUser":"admin","updateUser":null,"active":true,"year":"2022","xqbsm":"2133002592001","schoolName":"杭州市江心岛小学（北校区）","lng":"120.16554652124648","lat":"30.28860857115412","sequence":14,"bak1":null,"bak2":null,"bak3":null,"bak4":null,"bak5":null},{"id":22421,"createTime":"2022-06-23 14:03:03","updateTime":"2022-06-16 16:10:09","createUser":"admin","updateUser":null,"active":true,"year":"2022","xqbsm":"2133002592001","schoolName":"杭州市江心岛小学（北校区）","lng":"120.16563635179749","lat":"30.288811273302237","sequence":15,"bak1":null,"bak2":null,"bak3":null,"bak4":null,"bak5":null},{"id":22422,"createTime":"2022-06-23 14:03:03","updateTime":"2022-06-16 16:10:09","createUser":"admin","updateUser":null,"active":true,"year":"2022","xqbsm":"2133002592001","schoolName":"杭州市江心岛小学（北校区）","lng":"120.16700177617265","lat":"30.288936012875382","sequence":16,"bak1":null,"bak2":null,"bak3":null,"bak4":null,"bak5":null},{"id":22423,"createTime":"2022-06-23 14:03:03","updateTime":"2022-06-16 16:10:09","createUser":"admin","updateUser":null,"active":true,"year":"2022","xqbsm":"2133002592001","schoolName":"杭州市江心岛小学（北校区）","lng":"120.16738804754193","lat":"30.286020183453783","sequence":17,"bak1":null,"bak2":null,"bak3":null,"bak4":null,"bak5":null},{"id":22424,"createTime":"2022-06-23 14:03:03","updateTime":"2022-06-16 16:10:09","createUser":"admin","updateUser":null,"active":true,"year":"2022","xqbsm":"2133002592001","schoolName":"杭州市江心岛小学（北校区）","lng":"120.17216703285503","lat":"30.286675083246266","sequence":18,"bak1":null,"bak2":null,"bak3":null,"bak4":null,"bak5":null},{"id":22425,"createTime":"2022-06-23 14:03:03","updateTime":"2022-06-16 16:10:09","createUser":"admin","updateUser":null,"active":true,"year":"2022","xqbsm":"2133002592001","schoolName":"杭州市江心岛小学（北校区）","lng":"120.16605855538717","lat":"30.294439987020752","sequence":19,"bak1":null,"bak2":null,"bak3":null,"bak4":null,"bak5":null},{"id":22426,"createTime":"2022-06-23 14:03:03","updateTime":"2022-06-16 16:10:09","createUser":"admin","updateUser":null,"active":true,"year":"2022","xqbsm":"2133002592001","schoolName":"杭州市江心岛小学（北校区）","lng":"120.16451346991","lat":"30.29373836460762","sequence":20,"bak1":null,"bak2":null,"bak3":null,"bak4":null,"bak5":null},{"id":22427,"createTime":"2022-06-23 14:03:03","updateTime":"2022-06-16 16:10:09","createUser":"admin","updateUser":null,"active":true,"year":"2022","xqbsm":"2133002592001","schoolName":"杭州市江心岛小学（北校区）","lng":"120.16404635104482","lat":"30.295048055677622","sequence":21,"bak1":null,"bak2":null,"bak3":null,"bak4":null,"bak5":null},{"id":22428,"createTime":"2022-06-23 14:03:03","updateTime":"2022-06-16 16:10:09","createUser":"admin","updateUser":null,"active":true,"year":"2022","xqbsm":"2133002592001","schoolName":"杭州市江心岛小学（北校区）","lng":"120.16568126707298","lat":"30.2953131100542","sequence":22,"bak1":null,"bak2":null,"bak3":null,"bak4":null,"bak5":null}]}}