{"success":true,"code":2000,"message":"后台处理成功","result":{"earlyWarningStatus":null,"appSchoolPhotoInfoEntityList":[{"id":31024,"createTime":"2022-04-21 14:24:03","updateTime":null,"createUser":"bjqjyj","updateUser":null,"active":true,"schoolName":"浙江省杭州滨兴学校","year":"2022","thumbnailUrl":"https://rxyj.hzedu.gov.cn/hzjyFile/school/2021-10-21/affd83ef-994d-47d1-b373-202b94738cdd微信图片_20201119145806.jpg","orderBy":1,"xqbsm":"3133000185001"},{"id":31025,"createTime":"2022-04-21 14:24:03","updateTime":null,"createUser":"bjqjyj","updateUser":null,"active":true,"schoolName":"浙江省杭州滨兴学校","year":"2022","thumbnailUrl":"https://rxyj.hzedu.gov.cn/hzjyFile/school/2021-10-21/f38de1d9-ea69-4c52-947e-e8935fae906b浙江省杭州滨兴学校.jpg","orderBy":1,"xqbsm":"3133000185001"}],"mapInfoEntities":null,"appSchoolDistrictInfoEntityList":[{"id":23679,"createTime":"2022-04-21 14:24:03","updateTime":null,"createUser":"bjqjyj","updateUser":null,"active":true,"qxmc":"杭州市滨江区","year":"2022","schoolName":"浙江省杭州滨兴学校","xqbsm":"3133000185001","jdmc":"长河街道","sqmc":"江二社区","name":"滨兴东苑","streetCode":"330108002","streetName":"长河街道","communityCode":"330108002002000","communityName":"江二社区","xqbm":"330108008320","xqmc":"滨兴东苑","buildingNumber":"","buildingNumberZh":null,"xqId":"23679","fwsm":null,"dw":"","bak1":"否","lzhZh":"","isShow":"1","bak2":"户籍生","gajSchoolAddressEntities":null,"hjsrs":null,"jtthrs":null,"jthrs":null,"ybsrs":null,"hjsqrrs":null,"jtthqrrs":null,"jthqrrs":null,"ybsqrrs":null},{"id":23680,"createTime":"2022-04-21 14:24:03","updateTime":null,"createUser":"bjqjyj","updateUser":null,"active":true,"qxmc":"杭州市滨江区","year":"2022","schoolName":"浙江省杭州滨兴学校","xqbsm":"3133000185001","jdmc":"长河街道","sqmc":"江二社区","name":"滨兴北苑","streetCode":"330108002","streetName":"长河街道","communityCode":"330108002002000","communityName":"江二社区","xqbm":"330108008133","xqmc":"滨兴北苑","buildingNumber":"","buildingNumberZh":null,"xqId":"23680","fwsm":null,"dw":"","bak1":"否","lzhZh":"","isShow":"1","bak2":"户籍生","gajSchoolAddressEntities":null,"hjsrs":null,"jtthrs":null,"jthrs":null,"ybsrs":null,"hjsqrrs":null,"jtthqrrs":null,"jthqrrs":null,"ybsqrrs":null},{"id":23681,"createTime":"2022-04-21 14:24:03","updateTime":null,"createUser":"bjqjyj","updateUser":null,"active":true,"qxmc":"杭州市滨江区","year":"2022","schoolName":"浙江省杭州滨兴学校","xqbsm":"3133000185001","jdmc":"长河街道","sqmc":"江二社区","name":"滨兴家园","streetCode":"330108002","streetName":"长河街道","communityCode":"330108002002000","communityName":"江二社区","xqbm":"330108008416","xqmc":"滨兴家园","buildingNumber":"","buildingNumberZh":null,"xqId":"23681","fwsm":null,"dw":"","bak1":"否","lzhZh":"","isShow":"1","bak2":"户籍生","gajSchoolAddressEntities":null,"hjsrs":null,"jtthrs":null,"jthrs":null,"ybsrs":null,"hjsqrrs":null,"jtthqrrs":null,"jthqrrs":null,"ybsqrrs":null},{"id":23682,"createTime":"2022-04-21 14:24:03","updateTime":null,"createUser":"bjqjyj","updateUser":null,"active":true,"qxmc":"杭州市滨江区","year":"2022","schoolName":"浙江省杭州滨兴学校","xqbsm":"3133000185001","jdmc":"长河街道","sqmc":"江二社区","name":"滨兴小区","streetCode":"330108002","streetName":"长河街道","communityCode":"330108002002000","communityName":"江二社区","xqbm":"330108008318","xqmc":"滨兴小区","buildingNumber":"","buildingNumberZh":null,"xqId":"23682","fwsm":null,"dw":"","bak1":"否","lzhZh":"","isShow":"1","bak2":"户籍生","gajSchoolAddressEntities":null,"hjsrs":null,"jtthrs":null,"jthrs":null,"ybsrs":null,"hjsqrrs":null,"jtthqrrs":null,"jthqrrs":null,"ybsqrrs":null},{"id":23683,"createTime":"2022-04-21 14:24:03","updateTime":null,"createUser":"bjqjyj","updateUser":null,"active":true,"qxmc":"杭州市滨江区","year":"2022","schoolName":"浙江省杭州滨兴学校","xqbsm":"3133000185001","jdmc":"长河街道","sqmc":"江二社区","name":"滨兴西苑","streetCode":"330108002","streetName":"长河街道","communityCode":"330108002002000","communityName":"江二社区","xqbm":"330108008132","xqmc":"滨兴西苑","buildingNumber":"","buildingNumberZh":null,"xqId":"23683","fwsm":null,"dw":"","bak1":"否","lzhZh":"","isShow":"1","bak2":"户籍生","gajSchoolAddressEntities":null,"hjsrs":null,"jtthrs":null,"jthrs":null,"ybsrs":null,"hjsqrrs":null,"jtthqrrs":null,"jthqrrs":null,"ybsqrrs":null},{"id":23666,"createTime":"2022-04-21 14:24:03","updateTime":null,"createUser":"bjqjyj","updateUser":null,"active":true,"qxmc":"杭州市滨江区","year":"2022","schoolName":"浙江省杭州滨兴学校","xqbsm":"3133000185001","jdmc":"长河街道","sqmc":"江一社区","name":"长河街道江一社区","streetCode":"330108002","streetName":"长河街道","communityCode":"330108002001000","communityName":"江一社区","xqbm":"330108008015","xqmc":"长河街道江一社区","buildingNumber":"","buildingNumberZh":null,"xqId":"23666","fwsm":null,"dw":"","bak1":"否","lzhZh":"","isShow":"1","bak2":"户籍生","gajSchoolAddressEntities":null,"hjsrs":null,"jtthrs":null,"jthrs":null,"ybsrs":null,"hjsqrrs":null,"jtthqrrs":null,"jthqrrs":null,"ybsqrrs":null},{"id":23687,"createTime":"2022-04-21 14:24:03","updateTime":null,"createUser":"bjqjyj","updateUser":null,"active":true,"qxmc":"杭州市滨江区","year":"2022","schoolName":"浙江省杭州滨兴学校","xqbsm":"3133000185001","jdmc":"长河街道","sqmc":"江二社区","name":"长河街道江二社区","streetCode":"330108002","streetName":"长河街道","communityCode":"330108002002000","communityName":"江二社区","xqbm":"330108008013","xqmc":"长河街道江二社区","buildingNumber":"","buildingNumberZh":null,"xqId":"23687","fwsm":null,"dw":"","bak1":"否","lzhZh":"","isShow":"1","bak2":"户籍生","gajSchoolAddressEntities":null,"hjsrs":null,"jtthrs":null,"jthrs":null,"ybsrs":null,"hjsqrrs":null,"jtthqrrs":null,"jthqrrs":null,"ybsqrrs":null},{"id":23678,"createTime":"2022-04-21 14:24:03","updateTime":null,"createUser":"bjqjyj","updateUser":null,"active":true,"qxmc":"杭州市滨江区","year":"2022","schoolName":"浙江省杭州滨兴学校","xqbsm":"3133000185001","jdmc":"长河街道","sqmc":"江二社区","name":"江虹小区","streetCode":"330108002","streetName":"长河街道","communityCode":"330108002002000","communityName":"江二社区","xqbm":"330108008319","xqmc":"江虹小区","buildingNumber":"","buildingNumberZh":null,"xqId":"23678","fwsm":null,"dw":"","bak1":"否","lzhZh":"","isShow":"1","bak2":"户籍生","gajSchoolAddressEntities":null,"hjsrs":null,"jtthrs":null,"jthrs":null,"ybsrs":null,"hjsqrrs":null,"jtthqrrs":null,"jthqrrs":null,"ybsqrrs":null}],"appSchoolClassEntityList":[],"appSchoolInfoEntity":{"id":11733,"createTime":"2021-09-03 14:32:29","updateTime":"2022-04-21 14:24:03","createUser":null,"updateUser":"bjqjyj","active":true,"year":"2022","schoolCode":"3133000185","schoolName":"浙江省杭州滨兴学校","schoolType":"5","gmblx":"非民办","schoolOtherName":"杭州江南实验学校教育集团滨兴学校","address":"杭州市滨江区滨和路1799号","phoneNumber":null,"schoolWay":"杭州市滨江区滨和路1799号，滨兴小区北面。地点五号线、六号线长河站F出口处，东面方向300米左右。","recruitType":"户籍生","recruitCount":0,"registerCount":0,"sqznrs":0,"xssqrs":0,"shuntBd":null,"shuntWd":null,"schoolDetail":"    浙江省杭州滨兴学校，即杭州江南实验学校教育集团滨兴学校，创办于2004年，是杭州师范大学附属学校，高新区（滨江）第一所九年一贯制公办学校。学校占地面积33600㎡，建筑面积17190㎡，绿化面积18000㎡，绿地、花卉、树木层次分明，布局合理，环境优美。学校现有班级36个，其中小学24个，中学12个，现有公办教师103名，共有学生近1500名。\n    学校办学十七年来，坚持走文化立校之路，以“不断求阙，敢于超越”为校训，以“让每个学生都有表现自己的机会”为办学理念，以培养“有德性、有刚性、有悟性、有诗性的未来公民”为育人目标，追求“大气、正气、书生气”的教师文化，创建“和谐、简约、人文、开放”的学校文化。让师生拥有开阔的文化视野，创建富有特色的校本课程，通过建立教育实践基地，成立“四模”steam创客中心，举办“人文学堂”，开展特色活动，实施“小组合作制”教学模式，并积极进行对外教育教学交流，使学校文化更加多元，最终实现学生核心素养的提升。\n    2021年7月，滨兴学校作为第二批名校集团化学校成员加入杭州江南实验学校教育集团。","highTeacher":0,"middleTeacher":0,"primaryTeacher":0,"workerNumber":103,"shzt":2,"shztbz":"","absentNumber":103,"authorizedNumber":0,"schoolHonor":null,"enrollFileName":"滨兴学校2021新一年级招生方案.pdf","enrollFileUrl":"https://rxyj.hzedu.gov.cn/hzjyFile/policy/pdf/864b54ff-34b4-4f7f-b767-a2a7ce8d4bbf滨兴学校2021新一年级招生方案.pdf","zsjzxs":"0","enrollFileNameMid":null,"enrollFileUrlMid":null,"zsjzxsMid":null,"schoolFeature":null,"schoolMotto":null,"campusDistribution":null,"directPrimarySchoolCode":null,"directPrimarySchoolName":"浙江省杭州滨兴学校（小学部）","directMiddleSchoolCode":null,"directMiddleSchoolName":"","warningLevel":null,"warningYear":null,"warningPercent":null,"publishStatus":null,"yjfbzt":"2","bdIsshunt1":null,"bdShunt1":null,"wdIsshunt1":"1","wdShunt1":null,"bdIsshunt2":null,"bdShunt2":null,"wdIsshunt2":"1","wdShunt2":"false","bdIsshunt3":null,"bdShunt3":null,"wdIsshunt3":"1","wdShunt3":null,"schoolLogo":"https://rxyj.hzedu.gov.cn/hzjyFile/school/2022-04-21/53e8b335-47b3-44b4-9b43-f4f81ccf163a微信图片_20220421141143.png","schoolScope":"长河街道江一社区（不含春波小区、春波南苑、春波西苑、春波东苑）、江二社区。","schoolScopeMid":"杭州滨兴学校（小学部）","schoolTel":"56265010","schoolmasterName":null,"dkczbz":null,"schoolmasterDesc":null,"visitTimes":6722,"publishWarningDate":null,"lng":"120.204988","lat":"30.199535","dkczbsm":null,"splitFlowNum1":null,"splitFlowNum2":null,"splitFlowNum3":null,"seniorTeacherNum":0,"buildingAreaNum":17190,"hideFlag":"true","otherProvShunt1":"1","otherProvShunt1Mid":"2","otherProvShunt2":"1","otherProvShunt3":"1","otherSplitFlowNum1":null,"otherSplitFlowNum2":null,"otherSplitFlowNum3":null,"forecastClassNum1":4,"forecastClassNum2":4,"forecastClassNum3":4,"forecastClassPerson1":45,"forecastClassPerson2":45,"forecastClassPerson3":45,"forecastClassNum1Mid":4,"forecastClassNum2Mid":4,"forecastClassNum3Mid":4,"forecastClassPerson1Mid":45,"forecastClassPerson2Mid":45,"forecastClassPerson3Mid":45,"localShunt1":"2","localShunt1Mid":"2","localShunt2":"2","localShunt3":"2","oneSuper1":"2","oneSuper1Mid":"2","oneSuper2":"2","oneSuper3":"2","oneSuperTime1":"2021-08-31","oneSuperTime1Mid":null,"oneSuperTime2":"2020-08-31","oneSuperTime3":"2019-08-31","classTotalNum":36,"gradeTotalNum":0,"schoolAreaNum":33600,"gmblxSort":0,"generalSchoolName":null,"generalSchoolFlag":null,"visitCount":null,"szqmc":"滨江区","szqdm":"330108000000","key1":"6","xqbsm":"3133000185001","xxmc":"浙江省杭州滨兴学校","xqmc":"","xsrs":1496,"recruitTypeNewhzr":null,"schoolScopeNewhzr":null,"distnum":null,"disttime":null,"wdIsshunt1Mid":"1","wdIsshunt2Mid":"","wdIsshunt3Mid":"","publishStatusMid":"2","xqdt":"https://rxyj.hzedu.gov.cn/hzjyFile/school/2021-12-24/544ec947-7f5e-4038-be15-1a7bb513ebbf滨兴.png","showSchoolName":"浙江省杭州滨兴学校","appXcFlag":"0"},"appSchoolTypeInfoVOList":[{"id":11733,"createTime":null,"updateTime":null,"schoolType":"5","sqznrs":0,"xssqrs":0}],"appSchoolDistrictInfoEntityListNewHZR":[{"id":23666,"createTime":"2022-04-21 14:24:03","updateTime":null,"createUser":"bjqjyj","updateUser":null,"active":true,"qxmc":null,"year":"2022","schoolName":"浙江省杭州滨兴学校","xqbsm":"3133000185001","jdmc":"长河街道","sqmc":"江一社区","name":"长河街道江一社区","streetCode":"330108002","streetName":"长河街道","communityCode":"330108002001000","communityName":"江一社区","xqbm":"330108008015","xqmc":"长河街道江一社区","buildingNumber":"","buildingNumberZh":null,"xqId":"23666","fwsm":null,"dw":"","bak1":"否","lzhZh":null,"isShow":"1","bak2":"新杭州人","gajSchoolAddressEntities":null,"hjsrs":null,"jtthrs":null,"jthrs":null,"ybsrs":null,"hjsqrrs":null,"jtthqrrs":null,"jthqrrs":null,"ybsqrrs":null},{"id":23678,"createTime":"2022-04-21 14:24:03","updateTime":null,"createUser":"bjqjyj","updateUser":null,"active":true,"qxmc":null,"year":"2022","schoolName":"浙江省杭州滨兴学校","xqbsm":"3133000185001","jdmc":"长河街道","sqmc":"江二社区","name":"江虹小区","streetCode":"330108002","streetName":"长河街道","communityCode":"330108002002000","communityName":"江二社区","xqbm":"330108008319","xqmc":"江虹小区","buildingNumber":"","buildingNumberZh":null,"xqId":"23678","fwsm":null,"dw":"","bak1":"否","lzhZh":null,"isShow":"1","bak2":"新杭州人","gajSchoolAddressEntities":null,"hjsrs":null,"jtthrs":null,"jthrs":null,"ybsrs":null,"hjsqrrs":null,"jtthqrrs":null,"jthqrrs":null,"ybsqrrs":null},{"id":23679,"createTime":"2022-04-21 14:24:03","updateTime":null,"createUser":"bjqjyj","updateUser":null,"active":true,"qxmc":null,"year":"2022","schoolName":"浙江省杭州滨兴学校","xqbsm":"3133000185001","jdmc":"长河街道","sqmc":"江二社区","name":"滨兴东苑","streetCode":"330108002","streetName":"长河街道","communityCode":"330108002002000","communityName":"江二社区","xqbm":"330108008320","xqmc":"滨兴东苑","buildingNumber":"","buildingNumberZh":null,"xqId":"23679","fwsm":null,"dw":"","bak1":"否","lzhZh":null,"isShow":"1","bak2":"新杭州人","gajSchoolAddressEntities":null,"hjsrs":null,"jtthrs":null,"jthrs":null,"ybsrs":null,"hjsqrrs":null,"jtthqrrs":null,"jthqrrs":null,"ybsqrrs":null},{"id":23680,"createTime":"2022-04-21 14:24:03","updateTime":null,"createUser":"bjqjyj","updateUser":null,"active":true,"qxmc":null,"year":"2022","schoolName":"浙江省杭州滨兴学校","xqbsm":"3133000185001","jdmc":"长河街道","sqmc":"江二社区","name":"滨兴北苑","streetCode":"330108002","streetName":"长河街道","communityCode":"330108002002000","communityName":"江二社区","xqbm":"330108008133","xqmc":"滨兴北苑","buildingNumber":"","buildingNumberZh":null,"xqId":"23680","fwsm":null,"dw":"","bak1":"否","lzhZh":null,"isShow":"1","bak2":"新杭州人","gajSchoolAddressEntities":null,"hjsrs":null,"jtthrs":null,"jthrs":null,"ybsrs":null,"hjsqrrs":null,"jtthqrrs":null,"jthqrrs":null,"ybsqrrs":null},{"id":23681,"createTime":"2022-04-21 14:24:03","updateTime":null,"createUser":"bjqjyj","updateUser":null,"active":true,"qxmc":null,"year":"2022","schoolName":"浙江省杭州滨兴学校","xqbsm":"3133000185001","jdmc":"长河街道","sqmc":"江二社区","name":"滨兴家园","streetCode":"330108002","streetName":"长河街道","communityCode":"330108002002000","communityName":"江二社区","xqbm":"330108008416","xqmc":"滨兴家园","buildingNumber":"","buildingNumberZh":null,"xqId":"23681","fwsm":null,"dw":"","bak1":"否","lzhZh":null,"isShow":"1","bak2":"新杭州人","gajSchoolAddressEntities":null,"hjsrs":null,"jtthrs":null,"jthrs":null,"ybsrs":null,"hjsqrrs":null,"jtthqrrs":null,"jthqrrs":null,"ybsqrrs":null},{"id":23682,"createTime":"2022-04-21 14:24:03","updateTime":null,"createUser":"bjqjyj","updateUser":null,"active":true,"qxmc":null,"year":"2022","schoolName":"浙江省杭州滨兴学校","xqbsm":"3133000185001","jdmc":"长河街道","sqmc":"江二社区","name":"滨兴小区","streetCode":"330108002","streetName":"长河街道","communityCode":"330108002002000","communityName":"江二社区","xqbm":"330108008318","xqmc":"滨兴小区","buildingNumber":"","buildingNumberZh":null,"xqId":"23682","fwsm":null,"dw":"","bak1":"否","lzhZh":null,"isShow":"1","bak2":"新杭州人","gajSchoolAddressEntities":null,"hjsrs":null,"jtthrs":null,"jthrs":null,"ybsrs":null,"hjsqrrs":null,"jtthqrrs":null,"jthqrrs":null,"ybsqrrs":null},{"id":23687,"createTime":"2022-04-21 14:24:03","updateTime":null,"createUser":"bjqjyj","updateUser":null,"active":true,"qxmc":null,"year":"2022","schoolName":"浙江省杭州滨兴学校","xqbsm":"3133000185001","jdmc":"长河街道","sqmc":"江二社区","name":"长河街道江二社区","streetCode":"330108002","streetName":"长河街道","communityCode":"330108002002000","communityName":"江二社区","xqbm":"330108008013","xqmc":"长河街道江二社区","buildingNumber":"","buildingNumberZh":null,"xqId":"23687","fwsm":null,"dw":"","bak1":"否","lzhZh":null,"isShow":"1","bak2":"新杭州人","gajSchoolAddressEntities":null,"hjsrs":null,"jtthrs":null,"jthrs":null,"ybsrs":null,"hjsqrrs":null,"jtthqrrs":null,"jthqrrs":null,"ybsqrrs":null},{"id":23683,"createTime":"2022-04-21 14:24:03","updateTime":null,"createUser":"bjqjyj","updateUser":null,"active":true,"qxmc":null,"year":"2022","schoolName":"浙江省杭州滨兴学校","xqbsm":"3133000185001","jdmc":"长河街道","sqmc":"江二社区","name":"滨兴西苑","streetCode":"330108002","streetName":"长河街道","communityCode":"330108002002000","communityName":"江二社区","xqbm":"330108008132","xqmc":"滨兴西苑","buildingNumber":"","buildingNumberZh":null,"xqId":"23683","fwsm":null,"dw":"","bak1":"否","lzhZh":null,"isShow":"1","bak2":"新杭州人","gajSchoolAddressEntities":null,"hjsrs":null,"jtthrs":null,"jthrs":null,"ybsrs":null,"hjsqrrs":null,"jtthqrrs":null,"jthqrrs":null,"ybsqrrs":null},{"id":23664,"createTime":"2022-04-21 14:24:03","updateTime":null,"createUser":"bjqjyj","updateUser":null,"active":true,"qxmc":null,"year":"2022","schoolName":"浙江省杭州滨兴学校","xqbsm":"3133000185001","jdmc":"长河街道","sqmc":"江一社区","name":"滨兴小区","streetCode":"330108002","streetName":"长河街道","communityCode":"330108002001000","communityName":"江一社区","xqbm":"330108008318","xqmc":"滨兴小区","buildingNumber":"","buildingNumberZh":null,"xqId":"23664","fwsm":null,"dw":"","bak1":"否","lzhZh":null,"isShow":"2","bak2":"新杭州人","gajSchoolAddressEntities":null,"hjsrs":null,"jtthrs":null,"jthrs":null,"ybsrs":null,"hjsqrrs":null,"jtthqrrs":null,"jthqrrs":null,"ybsqrrs":null},{"id":23665,"createTime":"2022-04-21 14:24:03","updateTime":null,"createUser":"bjqjyj","updateUser":null,"active":true,"qxmc":null,"year":"2022","schoolName":"浙江省杭州滨兴学校","xqbsm":"3133000185001","jdmc":"长河街道","sqmc":"江一社区","name":"滨安路501号","streetCode":"330108002","streetName":"长河街道","communityCode":"330108002001000","communityName":"江一社区","xqbm":"330108008167","xqmc":"滨安路501号","buildingNumber":"","buildingNumberZh":null,"xqId":"23665","fwsm":null,"dw":"","bak1":"否","lzhZh":null,"isShow":"2","bak2":"新杭州人","gajSchoolAddressEntities":null,"hjsrs":null,"jtthrs":null,"jthrs":null,"ybsrs":null,"hjsqrrs":null,"jtthqrrs":null,"jthqrrs":null,"ybsqrrs":null},{"id":23661,"createTime":"2022-04-21 14:24:03","updateTime":null,"createUser":"bjqjyj","updateUser":null,"active":true,"qxmc":null,"year":"2022","schoolName":"浙江省杭州滨兴学校","xqbsm":"3133000185001","jdmc":"长河街道","sqmc":"江一社区","name":"江一社区非农组","streetCode":"330108002","streetName":"长河街道","communityCode":"330108002001000","communityName":"江一社区","xqbm":"330108008394","xqmc":"江一社区非农组","buildingNumber":"","buildingNumberZh":null,"xqId":"23661","fwsm":null,"dw":"","bak1":"否","lzhZh":null,"isShow":"2","bak2":"新杭州人","gajSchoolAddressEntities":null,"hjsrs":null,"jtthrs":null,"jthrs":null,"ybsrs":null,"hjsqrrs":null,"jtthqrrs":null,"jthqrrs":null,"ybsqrrs":null},{"id":23662,"createTime":"2022-04-21 14:24:03","updateTime":null,"createUser":"bjqjyj","updateUser":null,"active":true,"qxmc":null,"year":"2022","schoolName":"浙江省杭州滨兴学校","xqbsm":"3133000185001","jdmc":"长河街道","sqmc":"江一社区","name":"江虹小区","streetCode":"330108002","streetName":"长河街道","communityCode":"330108002001000","communityName":"江一社区","xqbm":"330108008319","xqmc":"江虹小区","buildingNumber":"","buildingNumberZh":null,"xqId":"23662","fwsm":null,"dw":"","bak1":"否","lzhZh":null,"isShow":"2","bak2":"新杭州人","gajSchoolAddressEntities":null,"hjsrs":null,"jtthrs":null,"jthrs":null,"ybsrs":null,"hjsqrrs":null,"jtthqrrs":null,"jthqrrs":null,"ybsqrrs":null},{"id":23663,"createTime":"2022-04-21 14:24:03","updateTime":null,"createUser":"bjqjyj","updateUser":null,"active":true,"qxmc":null,"year":"2022","schoolName":"浙江省杭州滨兴学校","xqbsm":"3133000185001","jdmc":"长河街道","sqmc":"江一社区","name":"滨兴东苑","streetCode":"330108002","streetName":"长河街道","communityCode":"330108002001000","communityName":"江一社区","xqbm":"330108008320","xqmc":"滨兴东苑","buildingNumber":"","buildingNumberZh":null,"xqId":"23663","fwsm":null,"dw":"","bak1":"否","lzhZh":null,"isShow":"2","bak2":"新杭州人","gajSchoolAddressEntities":null,"hjsrs":null,"jtthrs":null,"jthrs":null,"ybsrs":null,"hjsqrrs":null,"jtthqrrs":null,"jthqrrs":null,"ybsqrrs":null},{"id":34240,"createTime":"2022-04-21 14:24:03","updateTime":null,"createUser":"bjqjyj","updateUser":null,"active":true,"qxmc":null,"year":"2022","schoolName":"浙江省杭州滨兴学校","xqbsm":"3133000185001","jdmc":"长河街道","sqmc":"江二社区","name":"长河路590号","streetCode":"330108002","streetName":"长河街道","communityCode":"330108002002000","communityName":"江二社区","xqbm":"330108002002A0001","xqmc":"长河路590号","buildingNumber":"","buildingNumberZh":null,"xqId":"34240","fwsm":null,"dw":"","bak1":"否","lzhZh":null,"isShow":"2","bak2":"新杭州人","gajSchoolAddressEntities":null,"hjsrs":null,"jtthrs":null,"jthrs":null,"ybsrs":null,"hjsqrrs":null,"jtthqrrs":null,"jthqrrs":null,"ybsqrrs":null},{"id":23684,"createTime":"2022-04-21 14:24:03","updateTime":null,"createUser":"bjqjyj","updateUser":null,"active":true,"qxmc":null,"year":"2022","schoolName":"浙江省杭州滨兴学校","xqbsm":"3133000185001","jdmc":"长河街道","sqmc":"江二社区","name":"滨和路1799号","streetCode":"330108002","streetName":"长河街道","communityCode":"330108002002000","communityName":"江二社区","xqbm":"330108008200","xqmc":"滨和路1799号","buildingNumber":"","buildingNumberZh":null,"xqId":"23684","fwsm":null,"dw":"","bak1":"否","lzhZh":null,"isShow":"2","bak2":"新杭州人","gajSchoolAddressEntities":null,"hjsrs":null,"jtthrs":null,"jthrs":null,"ybsrs":null,"hjsqrrs":null,"jtthqrrs":null,"jthqrrs":null,"ybsqrrs":null},{"id":23685,"createTime":"2022-04-21 14:24:03","updateTime":null,"createUser":"bjqjyj","updateUser":null,"active":true,"qxmc":null,"year":"2022","schoolName":"浙江省杭州滨兴学校","xqbsm":"3133000185001","jdmc":"长河街道","sqmc":"江二社区","name":"滨安路760号","streetCode":"330108002","streetName":"长河街道","communityCode":"330108002002000","communityName":"江二社区","xqbm":"330108008198","xqmc":"滨安路760号","buildingNumber":"","buildingNumberZh":null,"xqId":"23685","fwsm":null,"dw":"","bak1":"否","lzhZh":null,"isShow":"2","bak2":"新杭州人","gajSchoolAddressEntities":null,"hjsrs":null,"jtthrs":null,"jthrs":null,"ybsrs":null,"hjsqrrs":null,"jtthqrrs":null,"jthqrrs":null,"ybsqrrs":null},{"id":23686,"createTime":"2022-04-21 14:24:03","updateTime":null,"createUser":"bjqjyj","updateUser":null,"active":true,"qxmc":null,"year":"2022","schoolName":"浙江省杭州滨兴学校","xqbsm":"3133000185001","jdmc":"长河街道","sqmc":"江二社区","name":"秋溢路368号","streetCode":"330108002","streetName":"长河街道","communityCode":"330108002002000","communityName":"江二社区","xqbm":"330108008199","xqmc":"秋溢路368号","buildingNumber":"","buildingNumberZh":null,"xqId":"23686","fwsm":null,"dw":"","bak1":"否","lzhZh":null,"isShow":"2","bak2":"新杭州人","gajSchoolAddressEntities":null,"hjsrs":null,"jtthrs":null,"jthrs":null,"ybsrs":null,"hjsqrrs":null,"jtthqrrs":null,"jthqrrs":null,"ybsqrrs":null},{"id":23677,"createTime":"2022-04-21 14:24:03","updateTime":null,"createUser":"bjqjyj","updateUser":null,"active":true,"qxmc":null,"year":"2022","schoolName":"浙江省杭州滨兴学校","xqbsm":"3133000185001","jdmc":"长河街道","sqmc":"江二社区","name":"江二社区汤家园","streetCode":"330108002","streetName":"长河街道","communityCode":"330108002002000","communityName":"江二社区","xqbm":"330108008396","xqmc":"江二社区汤家园","buildingNumber":"","buildingNumberZh":null,"xqId":"23677","fwsm":null,"dw":"","bak1":"否","lzhZh":null,"isShow":"2","bak2":"新杭州人","gajSchoolAddressEntities":null,"hjsrs":null,"jtthrs":null,"jthrs":null,"ybsrs":null,"hjsqrrs":null,"jtthqrrs":null,"jthqrrs":null,"ybsqrrs":null}],"appSchoolMapInfoEntities":[]}}