{"success":true,"code":2000,"message":"后台处理成功","result":{"earlyWarningStatus":null,"appSchoolPhotoInfoEntityList":[{"id":36491,"createTime":"2022-06-23 15:24:53","updateTime":null,"createUser":"gsqjyj","updateUser":null,"active":true,"schoolName":"浙大城市学院附属学校","year":"2022","thumbnailUrl":"https://rxyj.hzedu.gov.cn/hzjyFile/school/2022-05-20/82cb78ca-8a9c-4ee5-adb5-3d35934626304.jpg","orderBy":1,"xqbsm":"L000000500001"},{"id":36492,"createTime":"2022-06-23 15:24:53","updateTime":null,"createUser":"gsqjyj","updateUser":null,"active":true,"schoolName":"浙大城市学院附属学校","year":"2022","thumbnailUrl":"https://rxyj.hzedu.gov.cn/hzjyFile/school/2022-05-20/5f278078-11bf-4a99-a62e-419413c4d9282.jpg","orderBy":1,"xqbsm":"L000000500001"},{"id":36493,"createTime":"2022-06-23 15:24:53","updateTime":null,"createUser":"gsqjyj","updateUser":null,"active":true,"schoolName":"浙大城市学院附属学校","year":"2022","thumbnailUrl":"https://rxyj.hzedu.gov.cn/hzjyFile/school/2022-05-20/325f1f1c-0394-450c-b97e-274d0ba3916a3.jpg","orderBy":1,"xqbsm":"L000000500001"},{"id":36494,"createTime":"2022-06-23 15:24:53","updateTime":null,"createUser":"gsqjyj","updateUser":null,"active":true,"schoolName":"浙大城市学院附属学校","year":"2022","thumbnailUrl":"https://rxyj.hzedu.gov.cn/hzjyFile/school/2022-05-20/f62b17d4-3368-4284-b34c-497f7c75eba65.jpg","orderBy":1,"xqbsm":"L000000500001"},{"id":36495,"createTime":"2022-06-23 15:24:53","updateTime":null,"createUser":"gsqjyj","updateUser":null,"active":true,"schoolName":"浙大城市学院附属学校","year":"2022","thumbnailUrl":"https://rxyj.hzedu.gov.cn/hzjyFile/school/2022-05-20/c6593c79-920b-4827-aebb-48179eb429731.jpg","orderBy":1,"xqbsm":"L000000500001"}],"mapInfoEntities":null,"appSchoolDistrictInfoEntityList":[{"id":34405,"createTime":"2022-06-23 15:24:53","updateTime":null,"createUser":"gsqjyj","updateUser":null,"active":true,"qxmc":"杭州市拱墅区","year":"2022","schoolName":"浙大城市学院附属学校","xqbsm":"L000000500001","jdmc":"上塘街道","sqmc":"七古登社区","name":"传宸府","streetCode":"330105008","streetName":"上塘街道","communityCode":"330105008024000","communityName":"七古登社区","xqbm":"330105008024A0001","xqmc":"传宸府","buildingNumber":"","buildingNumberZh":null,"xqId":"34405","fwsm":null,"dw":"","bak1":"否","lzhZh":"","isShow":"1","bak2":"户籍生","gajSchoolAddressEntities":null,"hjsrs":null,"jtthrs":null,"jthrs":null,"ybsrs":null,"hjsqrrs":null,"jtthqrrs":null,"jthqrrs":null,"ybsqrrs":null},{"id":33894,"createTime":"2022-06-23 15:24:53","updateTime":null,"createUser":"gsqjyj","updateUser":null,"active":true,"qxmc":"杭州市拱墅区","year":"2022","schoolName":"浙大城市学院附属学校","xqbsm":"L000000500001","jdmc":"上塘街道","sqmc":"拱宸社区","name":"陆家坞","streetCode":"330105008","streetName":"上塘街道","communityCode":"330105008023000","communityName":"拱宸社区","xqbm":"330105008023A0002","xqmc":"陆家坞","buildingNumber":"","buildingNumberZh":null,"xqId":"33894","fwsm":null,"dw":"","bak1":"否","lzhZh":"","isShow":"1","bak2":"户籍生","gajSchoolAddressEntities":null,"hjsrs":null,"jtthrs":null,"jthrs":null,"ybsrs":null,"hjsqrrs":null,"jtthqrrs":null,"jthqrrs":null,"ybsqrrs":null},{"id":17443,"createTime":"2022-06-23 15:24:53","updateTime":null,"createUser":"gsqjyj","updateUser":null,"active":true,"qxmc":"杭州市拱墅区","year":"2022","schoolName":"浙大城市学院附属学校","xqbsm":"L000000500001","jdmc":"上塘街道","sqmc":"七古登社区","name":"七古登","streetCode":"330105008","streetName":"上塘街道","communityCode":"330105008024000","communityName":"七古登社区","xqbm":"2400010666","xqmc":"七古登","buildingNumber":"","buildingNumberZh":null,"xqId":"17443","fwsm":null,"dw":"","bak1":"否","lzhZh":"","isShow":"1","bak2":"户籍生","gajSchoolAddressEntities":null,"hjsrs":null,"jtthrs":null,"jthrs":null,"ybsrs":null,"hjsqrrs":null,"jtthqrrs":null,"jthqrrs":null,"ybsqrrs":null},{"id":20042,"createTime":"2022-06-23 15:24:53","updateTime":null,"createUser":"gsqjyj","updateUser":null,"active":true,"qxmc":"杭州市拱墅区","year":"2022","schoolName":"浙大城市学院附属学校","xqbsm":"L000000500001","jdmc":"上塘街道","sqmc":"善贤社区","name":"善贤人家","streetCode":"330105008","streetName":"上塘街道","communityCode":"330105008025000","communityName":"善贤社区","xqbm":"2500010678","xqmc":"善贤人家","buildingNumber":"","buildingNumberZh":null,"xqId":"20042","fwsm":null,"dw":"","bak1":"否","lzhZh":"","isShow":"1","bak2":"户籍生","gajSchoolAddressEntities":null,"hjsrs":null,"jtthrs":null,"jthrs":null,"ybsrs":null,"hjsqrrs":null,"jtthqrrs":null,"jthqrrs":null,"ybsqrrs":null},{"id":34012,"createTime":"2022-06-23 15:24:53","updateTime":null,"createUser":"gsqjyj","updateUser":null,"active":true,"qxmc":"杭州市拱墅区","year":"2022","schoolName":"浙大城市学院附属学校","xqbsm":"L000000500001","jdmc":"上塘街道","sqmc":"绍兴路社区","name":"绍兴新村","streetCode":"330105008","streetName":"上塘街道","communityCode":"330105008022000","communityName":"绍兴路社区","xqbm":"330105008022A0003","xqmc":"绍兴新村","buildingNumber":"","buildingNumberZh":null,"xqId":"34012","fwsm":null,"dw":"","bak1":"否","lzhZh":"","isShow":"1","bak2":"户籍生","gajSchoolAddressEntities":null,"hjsrs":null,"jtthrs":null,"jthrs":null,"ybsrs":null,"hjsqrrs":null,"jtthqrrs":null,"jthqrrs":null,"ybsqrrs":null},{"id":25275,"createTime":"2022-06-23 15:24:53","updateTime":null,"createUser":"gsqjyj","updateUser":null,"active":true,"qxmc":"杭州市拱墅区","year":"2022","schoolName":"浙大城市学院附属学校","xqbsm":"L000000500001","jdmc":"上塘街道","sqmc":"红建河社区","name":"沈塘湾","streetCode":"330105008","streetName":"上塘街道","communityCode":"330105008021000","communityName":"红建河社区","xqbm":"2100010696","xqmc":"沈塘湾","buildingNumber":"","buildingNumberZh":null,"xqId":"25275","fwsm":null,"dw":"","bak1":"否","lzhZh":"","isShow":"1","bak2":"户籍生","gajSchoolAddressEntities":null,"hjsrs":null,"jtthrs":null,"jthrs":null,"ybsrs":null,"hjsqrrs":null,"jtthqrrs":null,"jthqrrs":null,"ybsqrrs":null},{"id":17445,"createTime":"2022-06-23 15:24:53","updateTime":null,"createUser":"gsqjyj","updateUser":null,"active":true,"qxmc":"杭州市拱墅区","year":"2022","schoolName":"浙大城市学院附属学校","xqbsm":"L000000500001","jdmc":"上塘街道","sqmc":"七古登社区","name":"伟华苑","streetCode":"330105008","streetName":"上塘街道","communityCode":"330105008024000","communityName":"七古登社区","xqbm":"2400010668","xqmc":"伟华苑","buildingNumber":"","buildingNumberZh":null,"xqId":"17445","fwsm":null,"dw":"","bak1":"否","lzhZh":"","isShow":"1","bak2":"户籍生","gajSchoolAddressEntities":null,"hjsrs":null,"jtthrs":null,"jthrs":null,"ybsrs":null,"hjsqrrs":null,"jtthqrrs":null,"jthqrrs":null,"ybsqrrs":null},{"id":21847,"createTime":"2022-06-23 15:24:53","updateTime":null,"createUser":"gsqjyj","updateUser":null,"active":true,"qxmc":"杭州市拱墅区","year":"2022","schoolName":"浙大城市学院附属学校","xqbsm":"L000000500001","jdmc":"上塘街道","sqmc":"拱宸社区","name":"运河金麟府","streetCode":"330105008","streetName":"上塘街道","communityCode":"330105008023000","communityName":"拱宸社区","xqbm":"2300010682","xqmc":"运河金麟府","buildingNumber":"","buildingNumberZh":null,"xqId":"21847","fwsm":null,"dw":"","bak1":"否","lzhZh":"","isShow":"1","bak2":"户籍生","gajSchoolAddressEntities":null,"hjsrs":null,"jtthrs":null,"jthrs":null,"ybsrs":null,"hjsqrrs":null,"jtthqrrs":null,"jthqrrs":null,"ybsqrrs":null},{"id":21845,"createTime":"2022-06-23 15:24:53","updateTime":null,"createUser":"gsqjyj","updateUser":null,"active":true,"qxmc":"杭州市拱墅区","year":"2022","schoolName":"浙大城市学院附属学校","xqbsm":"L000000500001","jdmc":"上塘街道","sqmc":"拱宸社区","name":"宸铭府","streetCode":"330105008","streetName":"上塘街道","communityCode":"330105008023000","communityName":"拱宸社区","xqbm":"2300010680","xqmc":"宸铭府","buildingNumber":"","buildingNumberZh":null,"xqId":"21845","fwsm":null,"dw":"","bak1":"否","lzhZh":"","isShow":"1","bak2":"户籍生","gajSchoolAddressEntities":null,"hjsrs":null,"jtthrs":null,"jthrs":null,"ybsrs":null,"hjsqrrs":null,"jtthqrrs":null,"jthqrrs":null,"ybsqrrs":null},{"id":34406,"createTime":"2022-06-23 15:24:53","updateTime":null,"createUser":"gsqjyj","updateUser":null,"active":true,"qxmc":"杭州市拱墅区","year":"2022","schoolName":"浙大城市学院附属学校","xqbsm":"L000000500001","jdmc":"上塘街道","sqmc":"拱宸社区","name":"宸麟府","streetCode":"330105008","streetName":"上塘街道","communityCode":"330105008023000","communityName":"拱宸社区","xqbm":"330105008023A0005","xqmc":"宸麟府","buildingNumber":"","buildingNumberZh":null,"xqId":"34406","fwsm":null,"dw":"","bak1":"否","lzhZh":"","isShow":"1","bak2":"户籍生","gajSchoolAddressEntities":null,"hjsrs":null,"jtthrs":null,"jthrs":null,"ybsrs":null,"hjsqrrs":null,"jtthqrrs":null,"jthqrrs":null,"ybsqrrs":null}],"appSchoolClassEntityList":[],"appSchoolInfoEntity":{"id":14213,"createTime":"2022-04-28 12:10:26","updateTime":"2022-06-23 15:24:53","createUser":null,"updateUser":"gsqjyj","active":true,"year":"2022","schoolCode":"L000000500","schoolName":"浙大城市学院附属学校","schoolType":"5","gmblx":"非民办","schoolOtherName":null,"address":"杭州市树人街18号","phoneNumber":null,"schoolWay":"地铁5号线、公交26路","recruitType":"户籍生","recruitCount":0,"registerCount":0,"sqznrs":0,"xssqrs":0,"shuntBd":null,"shuntWd":null,"schoolDetail":"浙大城市学院附属学校是拱墅区政府和浙大城市学院合作办学的九年一贯制学校，小学部位于上塘街道树人街18号，占地40余亩，设计规模为36个班，计划于2022年4月底竣工，9月正式开学。学校内部装修于2月份全部完工，首年使用的办公家具和课桌椅也于3月到位。初中部位于蔡马东路，占地70余亩，设计规模42个班级，计划于2023年初竣工，9月正式开学。\n    浙大城市学院附属学校将以“儿童立场、家国情怀、未来眼光”为办学宗旨，以“求是启真、修远日新”为基本办学理念，以“促进每个生命自觉成长”为核心目标，充分发挥自身办学潜力和浙大城市学院的资源优势，为学区内适龄儿童提供优质而有特色的基础教育。","highTeacher":0,"middleTeacher":0,"primaryTeacher":0,"workerNumber":0,"shzt":2,"shztbz":"","absentNumber":0,"authorizedNumber":0,"schoolHonor":null,"enrollFileName":null,"enrollFileUrl":null,"zsjzxs":null,"enrollFileNameMid":null,"enrollFileUrlMid":null,"zsjzxsMid":null,"schoolFeature":null,"schoolMotto":null,"campusDistribution":null,"directPrimarySchoolCode":null,"directPrimarySchoolName":"浙大城市学院附属学校（小学部）","directMiddleSchoolCode":null,"directMiddleSchoolName":"","warningLevel":null,"warningYear":null,"warningPercent":null,"publishStatus":null,"yjfbzt":"2","bdIsshunt1":null,"bdShunt1":null,"wdIsshunt1":"1","wdShunt1":null,"bdIsshunt2":null,"bdShunt2":null,"wdIsshunt2":"1","wdShunt2":"false","bdIsshunt3":null,"bdShunt3":null,"wdIsshunt3":"1","wdShunt3":null,"schoolLogo":"https://rxyj.hzedu.gov.cn/hzjyFile/school/2022-05-20/456cc2b1-9ffc-47d3-844c-3be590f30ca66.jpg","schoolScope":"上塘路以东、湖州街以南、上塘河以西、绍兴路以北区域适龄儿童。","schoolScopeMid":null,"schoolTel":"0571-81960826","schoolmasterName":null,"dkczbz":null,"schoolmasterDesc":null,"visitTimes":2787,"publishWarningDate":null,"lng":"120.158453","lat":"30.322633","dkczbsm":null,"splitFlowNum1":null,"splitFlowNum2":null,"splitFlowNum3":null,"seniorTeacherNum":0,"buildingAreaNum":0,"hideFlag":"true","otherProvShunt1":null,"otherProvShunt1Mid":null,"otherProvShunt2":null,"otherProvShunt3":null,"otherSplitFlowNum1":null,"otherSplitFlowNum2":null,"otherSplitFlowNum3":null,"forecastClassNum1":2,"forecastClassNum2":2,"forecastClassNum3":2,"forecastClassPerson1":45,"forecastClassPerson2":45,"forecastClassPerson3":45,"forecastClassNum1Mid":0,"forecastClassNum2Mid":0,"forecastClassNum3Mid":0,"forecastClassPerson1Mid":0,"forecastClassPerson2Mid":0,"forecastClassPerson3Mid":0,"localShunt1":null,"localShunt1Mid":null,"localShunt2":null,"localShunt3":null,"oneSuper1":null,"oneSuper1Mid":null,"oneSuper2":null,"oneSuper3":null,"oneSuperTime1":null,"oneSuperTime1Mid":null,"oneSuperTime2":null,"oneSuperTime3":null,"classTotalNum":0,"gradeTotalNum":0,"schoolAreaNum":0,"gmblxSort":0,"generalSchoolName":null,"generalSchoolFlag":null,"visitCount":null,"szqmc":"拱墅区","szqdm":"330105000000","key1":"4","xqbsm":"L000000500001","xxmc":"浙大城市学院附属学校","xqmc":null,"xsrs":0,"recruitTypeNewhzr":null,"schoolScopeNewhzr":null,"distnum":null,"disttime":null,"wdIsshunt1Mid":"5","wdIsshunt2Mid":"","wdIsshunt3Mid":"","publishStatusMid":"2","xqdt":null,"showSchoolName":"浙大城市学院附属学校","appXcFlag":"0"},"appSchoolTypeInfoVOList":[{"id":14213,"createTime":null,"updateTime":null,"schoolType":"5","sqznrs":0,"xssqrs":0}],"appSchoolDistrictInfoEntityListNewHZR":[{"id":25275,"createTime":"2022-06-23 15:24:53","updateTime":null,"createUser":"gsqjyj","updateUser":null,"active":true,"qxmc":null,"year":"2022","schoolName":"浙大城市学院附属学校","xqbsm":"L000000500001","jdmc":"上塘街道","sqmc":"红建河社区","name":"沈塘湾","streetCode":"330105008","streetName":"上塘街道","communityCode":"330105008021000","communityName":"红建河社区","xqbm":"2100010696","xqmc":"沈塘湾","buildingNumber":"","buildingNumberZh":null,"xqId":"25275","fwsm":null,"dw":"","bak1":"否","lzhZh":null,"isShow":"1","bak2":"新杭州人","gajSchoolAddressEntities":null,"hjsrs":null,"jtthrs":null,"jthrs":null,"ybsrs":null,"hjsqrrs":null,"jtthqrrs":null,"jthqrrs":null,"ybsqrrs":null},{"id":34012,"createTime":"2022-06-23 15:24:53","updateTime":null,"createUser":"gsqjyj","updateUser":null,"active":true,"qxmc":null,"year":"2022","schoolName":"浙大城市学院附属学校","xqbsm":"L000000500001","jdmc":"上塘街道","sqmc":"绍兴路社区","name":"绍兴新村","streetCode":"330105008","streetName":"上塘街道","communityCode":"330105008022000","communityName":"绍兴路社区","xqbm":"330105008022A0003","xqmc":"绍兴新村","buildingNumber":"","buildingNumberZh":null,"xqId":"34012","fwsm":null,"dw":"","bak1":"否","lzhZh":null,"isShow":"1","bak2":"新杭州人","gajSchoolAddressEntities":null,"hjsrs":null,"jtthrs":null,"jthrs":null,"ybsrs":null,"hjsqrrs":null,"jtthqrrs":null,"jthqrrs":null,"ybsqrrs":null},{"id":21847,"createTime":"2022-06-23 15:24:53","updateTime":null,"createUser":"gsqjyj","updateUser":null,"active":true,"qxmc":null,"year":"2022","schoolName":"浙大城市学院附属学校","xqbsm":"L000000500001","jdmc":"上塘街道","sqmc":"拱宸社区","name":"运河金麟府","streetCode":"330105008","streetName":"上塘街道","communityCode":"330105008023000","communityName":"拱宸社区","xqbm":"2300010682","xqmc":"运河金麟府","buildingNumber":"","buildingNumberZh":null,"xqId":"21847","fwsm":null,"dw":"","bak1":"否","lzhZh":null,"isShow":"1","bak2":"新杭州人","gajSchoolAddressEntities":null,"hjsrs":null,"jtthrs":null,"jthrs":null,"ybsrs":null,"hjsqrrs":null,"jtthqrrs":null,"jthqrrs":null,"ybsqrrs":null},{"id":34406,"createTime":"2022-06-23 15:24:53","updateTime":null,"createUser":"gsqjyj","updateUser":null,"active":true,"qxmc":null,"year":"2022","schoolName":"浙大城市学院附属学校","xqbsm":"L000000500001","jdmc":"上塘街道","sqmc":"拱宸社区","name":"宸麟府","streetCode":"330105008","streetName":"上塘街道","communityCode":"330105008023000","communityName":"拱宸社区","xqbm":"330105008023A0005","xqmc":"宸麟府","buildingNumber":"","buildingNumberZh":null,"xqId":"34406","fwsm":null,"dw":"","bak1":"否","lzhZh":null,"isShow":"1","bak2":"新杭州人","gajSchoolAddressEntities":null,"hjsrs":null,"jtthrs":null,"jthrs":null,"ybsrs":null,"hjsqrrs":null,"jtthqrrs":null,"jthqrrs":null,"ybsqrrs":null},{"id":21845,"createTime":"2022-06-23 15:24:53","updateTime":null,"createUser":"gsqjyj","updateUser":null,"active":true,"qxmc":null,"year":"2022","schoolName":"浙大城市学院附属学校","xqbsm":"L000000500001","jdmc":"上塘街道","sqmc":"拱宸社区","name":"宸铭府","streetCode":"330105008","streetName":"上塘街道","communityCode":"330105008023000","communityName":"拱宸社区","xqbm":"2300010680","xqmc":"宸铭府","buildingNumber":"","buildingNumberZh":null,"xqId":"21845","fwsm":null,"dw":"","bak1":"否","lzhZh":null,"isShow":"1","bak2":"新杭州人","gajSchoolAddressEntities":null,"hjsrs":null,"jtthrs":null,"jthrs":null,"ybsrs":null,"hjsqrrs":null,"jtthqrrs":null,"jthqrrs":null,"ybsqrrs":null},{"id":33894,"createTime":"2022-06-23 15:24:53","updateTime":null,"createUser":"gsqjyj","updateUser":null,"active":true,"qxmc":null,"year":"2022","schoolName":"浙大城市学院附属学校","xqbsm":"L000000500001","jdmc":"上塘街道","sqmc":"拱宸社区","name":"陆家坞","streetCode":"330105008","streetName":"上塘街道","communityCode":"330105008023000","communityName":"拱宸社区","xqbm":"330105008023A0002","xqmc":"陆家坞","buildingNumber":"","buildingNumberZh":null,"xqId":"33894","fwsm":null,"dw":"","bak1":"否","lzhZh":null,"isShow":"1","bak2":"新杭州人","gajSchoolAddressEntities":null,"hjsrs":null,"jtthrs":null,"jthrs":null,"ybsrs":null,"hjsqrrs":null,"jtthqrrs":null,"jthqrrs":null,"ybsqrrs":null},{"id":17445,"createTime":"2022-06-23 15:24:53","updateTime":null,"createUser":"gsqjyj","updateUser":null,"active":true,"qxmc":null,"year":"2022","schoolName":"浙大城市学院附属学校","xqbsm":"L000000500001","jdmc":"上塘街道","sqmc":"七古登社区","name":"伟华苑","streetCode":"330105008","streetName":"上塘街道","communityCode":"330105008024000","communityName":"七古登社区","xqbm":"2400010668","xqmc":"伟华苑","buildingNumber":"","buildingNumberZh":null,"xqId":"17445","fwsm":null,"dw":"","bak1":"否","lzhZh":null,"isShow":"1","bak2":"新杭州人","gajSchoolAddressEntities":null,"hjsrs":null,"jtthrs":null,"jthrs":null,"ybsrs":null,"hjsqrrs":null,"jtthqrrs":null,"jthqrrs":null,"ybsqrrs":null},{"id":17443,"createTime":"2022-06-23 15:24:53","updateTime":null,"createUser":"gsqjyj","updateUser":null,"active":true,"qxmc":null,"year":"2022","schoolName":"浙大城市学院附属学校","xqbsm":"L000000500001","jdmc":"上塘街道","sqmc":"七古登社区","name":"七古登","streetCode":"330105008","streetName":"上塘街道","communityCode":"330105008024000","communityName":"七古登社区","xqbm":"2400010666","xqmc":"七古登","buildingNumber":"","buildingNumberZh":null,"xqId":"17443","fwsm":null,"dw":"","bak1":"否","lzhZh":null,"isShow":"1","bak2":"新杭州人","gajSchoolAddressEntities":null,"hjsrs":null,"jtthrs":null,"jthrs":null,"ybsrs":null,"hjsqrrs":null,"jtthqrrs":null,"jthqrrs":null,"ybsqrrs":null},{"id":34405,"createTime":"2022-06-23 15:24:53","updateTime":null,"createUser":"gsqjyj","updateUser":null,"active":true,"qxmc":null,"year":"2022","schoolName":"浙大城市学院附属学校","xqbsm":"L000000500001","jdmc":"上塘街道","sqmc":"七古登社区","name":"传宸府","streetCode":"330105008","streetName":"上塘街道","communityCode":"330105008024000","communityName":"七古登社区","xqbm":"330105008024A0001","xqmc":"传宸府","buildingNumber":"","buildingNumberZh":null,"xqId":"34405","fwsm":null,"dw":"","bak1":"否","lzhZh":null,"isShow":"1","bak2":"新杭州人","gajSchoolAddressEntities":null,"hjsrs":null,"jtthrs":null,"jthrs":null,"ybsrs":null,"hjsqrrs":null,"jtthqrrs":null,"jthqrrs":null,"ybsqrrs":null},{"id":20042,"createTime":"2022-06-23 15:24:53","updateTime":null,"createUser":"gsqjyj","updateUser":null,"active":true,"qxmc":null,"year":"2022","schoolName":"浙大城市学院附属学校","xqbsm":"L000000500001","jdmc":"上塘街道","sqmc":"善贤社区","name":"善贤人家","streetCode":"330105008","streetName":"上塘街道","communityCode":"330105008025000","communityName":"善贤社区","xqbm":"2500010678","xqmc":"善贤人家","buildingNumber":"","buildingNumberZh":null,"xqId":"20042","fwsm":null,"dw":"","bak1":"否","lzhZh":null,"isShow":"1","bak2":"新杭州人","gajSchoolAddressEntities":null,"hjsrs":null,"jtthrs":null,"jthrs":null,"ybsrs":null,"hjsqrrs":null,"jtthqrrs":null,"jthqrrs":null,"ybsqrrs":null},{"id":34069,"createTime":"2022-06-23 15:24:53","updateTime":null,"createUser":"gsqjyj","updateUser":null,"active":true,"qxmc":null,"year":"2022","schoolName":"浙大城市学院附属学校","xqbsm":"L000000500001","jdmc":"上塘街道","sqmc":"红建河社区","name":"沈半路","streetCode":"330105008","streetName":"上塘街道","communityCode":"330105008021000","communityName":"红建河社区","xqbm":"330105008021A0003","xqmc":"沈半路","buildingNumber":"","buildingNumberZh":null,"xqId":"34069","fwsm":null,"dw":"","bak1":"否","lzhZh":null,"isShow":"2","bak2":"新杭州人","gajSchoolAddressEntities":null,"hjsrs":null,"jtthrs":null,"jthrs":null,"ybsrs":null,"hjsqrrs":null,"jtthqrrs":null,"jthqrrs":null,"ybsqrrs":null},{"id":34073,"createTime":"2022-06-23 15:24:53","updateTime":null,"createUser":"gsqjyj","updateUser":null,"active":true,"qxmc":null,"year":"2022","schoolName":"浙大城市学院附属学校","xqbsm":"L000000500001","jdmc":"上塘街道","sqmc":"绍兴路社区","name":"沈塘湾","streetCode":"330105008","streetName":"上塘街道","communityCode":"330105008022000","communityName":"绍兴路社区","xqbm":"330105008022A0005","xqmc":"沈塘湾","buildingNumber":"","buildingNumberZh":null,"xqId":"34073","fwsm":null,"dw":"","bak1":"否","lzhZh":null,"isShow":"2","bak2":"新杭州人","gajSchoolAddressEntities":null,"hjsrs":null,"jtthrs":null,"jthrs":null,"ybsrs":null,"hjsqrrs":null,"jtthqrrs":null,"jthqrrs":null,"ybsqrrs":null},{"id":33984,"createTime":"2022-06-23 15:24:53","updateTime":null,"createUser":"gsqjyj","updateUser":null,"active":true,"qxmc":null,"year":"2022","schoolName":"浙大城市学院附属学校","xqbsm":"L000000500001","jdmc":"上塘街道","sqmc":"绍兴路社区","name":"绍兴路","streetCode":"330105008","streetName":"上塘街道","communityCode":"330105008022000","communityName":"绍兴路社区","xqbm":"330105008022A0002","xqmc":"绍兴路","buildingNumber":"","buildingNumberZh":null,"xqId":"33984","fwsm":null,"dw":"","bak1":"否","lzhZh":null,"isShow":"2","bak2":"新杭州人","gajSchoolAddressEntities":null,"hjsrs":null,"jtthrs":null,"jthrs":null,"ybsrs":null,"hjsqrrs":null,"jtthqrrs":null,"jthqrrs":null,"ybsqrrs":null},{"id":34488,"createTime":"2022-06-23 15:24:53","updateTime":null,"createUser":"gsqjyj","updateUser":null,"active":true,"qxmc":null,"year":"2022","schoolName":"浙大城市学院附属学校","xqbsm":"L000000500001","jdmc":"上塘街道","sqmc":"拱宸社区","name":"上塘路","streetCode":"330105008","streetName":"上塘街道","communityCode":"330105008023000","communityName":"拱宸社区","xqbm":"330105008023A0007","xqmc":"上塘路","buildingNumber":"９４２弄","buildingNumberZh":null,"xqId":"34488","fwsm":null,"dw":"","bak1":"否","lzhZh":null,"isShow":"2","bak2":"新杭州人","gajSchoolAddressEntities":null,"hjsrs":null,"jtthrs":null,"jthrs":null,"ybsrs":null,"hjsqrrs":null,"jtthqrrs":null,"jthqrrs":null,"ybsqrrs":null},{"id":33897,"createTime":"2022-06-23 15:24:53","updateTime":null,"createUser":"gsqjyj","updateUser":null,"active":true,"qxmc":null,"year":"2022","schoolName":"浙大城市学院附属学校","xqbsm":"L000000500001","jdmc":"上塘街道","sqmc":"拱宸社区","name":"嘉兴东路","streetCode":"330105008","streetName":"上塘街道","communityCode":"330105008023000","communityName":"拱宸社区","xqbm":"330105008023A0003","xqmc":"嘉兴东路","buildingNumber":"","buildingNumberZh":null,"xqId":"33897","fwsm":null,"dw":"","bak1":"否","lzhZh":null,"isShow":"2","bak2":"新杭州人","gajSchoolAddressEntities":null,"hjsrs":null,"jtthrs":null,"jthrs":null,"ybsrs":null,"hjsqrrs":null,"jtthqrrs":null,"jthqrrs":null,"ybsqrrs":null},{"id":34489,"createTime":"2022-06-23 15:24:53","updateTime":null,"createUser":"gsqjyj","updateUser":null,"active":true,"qxmc":null,"year":"2022","schoolName":"浙大城市学院附属学校","xqbsm":"L000000500001","jdmc":"上塘街道","sqmc":"拱宸社区","name":"台州路","streetCode":"330105008","streetName":"上塘街道","communityCode":"330105008023000","communityName":"拱宸社区","xqbm":"330105008023A0008","xqmc":"台州路","buildingNumber":"１８７弄","buildingNumberZh":null,"xqId":"34489","fwsm":null,"dw":"","bak1":"否","lzhZh":null,"isShow":"2","bak2":"新杭州人","gajSchoolAddressEntities":null,"hjsrs":null,"jtthrs":null,"jthrs":null,"ybsrs":null,"hjsqrrs":null,"jtthqrrs":null,"jthqrrs":null,"ybsqrrs":null},{"id":34010,"createTime":"2022-06-23 15:24:53","updateTime":null,"createUser":"gsqjyj","updateUser":null,"active":true,"qxmc":null,"year":"2022","schoolName":"浙大城市学院附属学校","xqbsm":"L000000500001","jdmc":"上塘街道","sqmc":"拱宸社区","name":"上塘镇","streetCode":"330105008","streetName":"上塘街道","communityCode":"330105008023000","communityName":"拱宸社区","xqbm":"330105008023A0004","xqmc":"上塘镇","buildingNumber":"","buildingNumberZh":null,"xqId":"34010","fwsm":null,"dw":"","bak1":"否","lzhZh":null,"isShow":"2","bak2":"新杭州人","gajSchoolAddressEntities":null,"hjsrs":null,"jtthrs":null,"jthrs":null,"ybsrs":null,"hjsqrrs":null,"jtthqrrs":null,"jthqrrs":null,"ybsqrrs":null},{"id":33892,"createTime":"2022-06-23 15:24:53","updateTime":null,"createUser":"gsqjyj","updateUser":null,"active":true,"qxmc":null,"year":"2022","schoolName":"浙大城市学院附属学校","xqbsm":"L000000500001","jdmc":"上塘街道","sqmc":"拱宸社区","name":"湖州东路","streetCode":"330105008","streetName":"上塘街道","communityCode":"330105008023000","communityName":"拱宸社区","xqbm":"330105008023A0001","xqmc":"湖州东路","buildingNumber":"","buildingNumberZh":null,"xqId":"33892","fwsm":null,"dw":"","bak1":"否","lzhZh":null,"isShow":"2","bak2":"新杭州人","gajSchoolAddressEntities":null,"hjsrs":null,"jtthrs":null,"jthrs":null,"ybsrs":null,"hjsqrrs":null,"jtthqrrs":null,"jthqrrs":null,"ybsqrrs":null},{"id":34419,"createTime":"2022-06-23 15:24:53","updateTime":null,"createUser":"gsqjyj","updateUser":null,"active":true,"qxmc":null,"year":"2022","schoolName":"浙大城市学院附属学校","xqbsm":"L000000500001","jdmc":"上塘街道","sqmc":"七古登社区","name":"舟山东路","streetCode":"330105008","streetName":"上塘街道","communityCode":"330105008024000","communityName":"七古登社区","xqbm":"330105008024A0004","xqmc":"舟山东路","buildingNumber":"","buildingNumberZh":null,"xqId":"34419","fwsm":null,"dw":"","bak1":"否","lzhZh":null,"isShow":"2","bak2":"新杭州人","gajSchoolAddressEntities":null,"hjsrs":null,"jtthrs":null,"jthrs":null,"ybsrs":null,"hjsqrrs":null,"jtthqrrs":null,"jthqrrs":null,"ybsqrrs":null},{"id":34476,"createTime":"2022-06-23 15:24:53","updateTime":null,"createUser":"gsqjyj","updateUser":null,"active":true,"qxmc":null,"year":"2022","schoolName":"浙大城市学院附属学校","xqbsm":"L000000500001","jdmc":"上塘街道","sqmc":"七古登社区","name":"湖州街","streetCode":"330105008","streetName":"上塘街道","communityCode":"330105008024000","communityName":"七古登社区","xqbm":"330105008024A0005","xqmc":"湖州街","buildingNumber":"","buildingNumberZh":null,"xqId":"34476","fwsm":null,"dw":"","bak1":"否","lzhZh":null,"isShow":"2","bak2":"新杭州人","gajSchoolAddressEntities":null,"hjsrs":null,"jtthrs":null,"jthrs":null,"ybsrs":null,"hjsqrrs":null,"jtthqrrs":null,"jthqrrs":null,"ybsqrrs":null},{"id":34477,"createTime":"2022-06-23 15:24:53","updateTime":null,"createUser":"gsqjyj","updateUser":null,"active":true,"qxmc":null,"year":"2022","schoolName":"浙大城市学院附属学校","xqbsm":"L000000500001","jdmc":"上塘街道","sqmc":"七古登社区","name":"台州路","streetCode":"330105008","streetName":"上塘街道","communityCode":"330105008024000","communityName":"七古登社区","xqbm":"330105008024A0006","xqmc":"台州路","buildingNumber":"","buildingNumberZh":null,"xqId":"34477","fwsm":null,"dw":"","bak1":"否","lzhZh":null,"isShow":"2","bak2":"新杭州人","gajSchoolAddressEntities":null,"hjsrs":null,"jtthrs":null,"jthrs":null,"ybsrs":null,"hjsqrrs":null,"jtthqrrs":null,"jthqrrs":null,"ybsqrrs":null},{"id":34417,"createTime":"2022-06-23 15:24:53","updateTime":null,"createUser":"gsqjyj","updateUser":null,"active":true,"qxmc":null,"year":"2022","schoolName":"浙大城市学院附属学校","xqbsm":"L000000500001","jdmc":"上塘街道","sqmc":"七古登社区","name":"上塘镇","streetCode":"330105008","streetName":"上塘街道","communityCode":"330105008024000","communityName":"七古登社区","xqbm":"330105008024A0003","xqmc":"上塘镇","buildingNumber":"七古登、树人街","buildingNumberZh":null,"xqId":"34417","fwsm":null,"dw":"","bak1":"否","lzhZh":null,"isShow":"2","bak2":"新杭州人","gajSchoolAddressEntities":null,"hjsrs":null,"jtthrs":null,"jthrs":null,"ybsrs":null,"hjsqrrs":null,"jtthqrrs":null,"jthqrrs":null,"ybsqrrs":null},{"id":34473,"createTime":"2022-06-23 15:24:53","updateTime":null,"createUser":"gsqjyj","updateUser":null,"active":true,"qxmc":null,"year":"2022","schoolName":"浙大城市学院附属学校","xqbsm":"L000000500001","jdmc":"上塘街道","sqmc":"善贤社区","name":"上塘镇","streetCode":"330105008","streetName":"上塘街道","communityCode":"330105008025000","communityName":"善贤社区","xqbm":"330105008025A0003","xqmc":"上塘镇","buildingNumber":"善贤坝、陆家村","buildingNumberZh":null,"xqId":"34473","fwsm":null,"dw":"","bak1":"否","lzhZh":null,"isShow":"2","bak2":"新杭州人","gajSchoolAddressEntities":null,"hjsrs":null,"jtthrs":null,"jthrs":null,"ybsrs":null,"hjsqrrs":null,"jtthqrrs":null,"jthqrrs":null,"ybsqrrs":null},{"id":34070,"createTime":"2022-06-23 15:24:53","updateTime":null,"createUser":"gsqjyj","updateUser":null,"active":true,"qxmc":null,"year":"2022","schoolName":"浙大城市学院附属学校","xqbsm":"L000000500001","jdmc":"上塘街道","sqmc":"善贤社区","name":"沈半路","streetCode":"330105008","streetName":"上塘街道","communityCode":"330105008025000","communityName":"善贤社区","xqbm":"330105008025A0001","xqmc":"沈半路","buildingNumber":"","buildingNumberZh":null,"xqId":"34070","fwsm":null,"dw":"","bak1":"否","lzhZh":null,"isShow":"2","bak2":"新杭州人","gajSchoolAddressEntities":null,"hjsrs":null,"jtthrs":null,"jthrs":null,"ybsrs":null,"hjsqrrs":null,"jtthqrrs":null,"jthqrrs":null,"ybsqrrs":null}],"appSchoolMapInfoEntities":[{"id":22519,"createTime":"2022-06-23 15:24:53","updateTime":"2022-06-23 15:12:55","createUser":"gsqjyj","updateUser":null,"active":true,"year":"2022","xqbsm":"L000000500001","schoolName":"浙大城市学院附属学校","lng":"120.15235041330492","lat":"30.33077709291976","sequence":1,"bak1":null,"bak2":null,"bak3":null,"bak4":null,"bak5":null},{"id":22520,"createTime":"2022-06-23 15:24:53","updateTime":"2022-06-23 15:12:55","createUser":"gsqjyj","updateUser":null,"active":true,"year":"2022","xqbsm":"L000000500001","schoolName":"浙大城市学院附属学校","lng":"120.15977041681732","lat":"30.331353762641644","sequence":2,"bak1":null,"bak2":null,"bak3":null,"bak4":null,"bak5":null},{"id":22521,"createTime":"2022-06-23 15:24:53","updateTime":"2022-06-23 15:12:55","createUser":"gsqjyj","updateUser":null,"active":true,"year":"2022","xqbsm":"L000000500001","schoolName":"浙大城市学院附属学校","lng":"120.16311211331444","lat":"30.33141610510883","sequence":3,"bak1":null,"bak2":null,"bak3":null,"bak4":null,"bak5":null},{"id":22522,"createTime":"2022-06-23 15:24:53","updateTime":"2022-06-23 15:12:55","createUser":"gsqjyj","updateUser":null,"active":true,"year":"2022","xqbsm":"L000000500001","schoolName":"浙大城市学院附属学校","lng":"120.16620228426876","lat":"30.328361277073345","sequence":4,"bak1":null,"bak2":null,"bak3":null,"bak4":null,"bak5":null},{"id":22523,"createTime":"2022-06-23 15:24:53","updateTime":"2022-06-23 15:12:55","createUser":"gsqjyj","updateUser":null,"active":true,"year":"2022","xqbsm":"L000000500001","schoolName":"浙大城市学院附属学校","lng":"120.1702087268432","lat":"30.323311257218467","sequence":5,"bak1":null,"bak2":null,"bak3":null,"bak4":null,"bak5":null},{"id":22524,"createTime":"2022-06-23 15:24:53","updateTime":"2022-06-23 15:12:55","createUser":"gsqjyj","updateUser":null,"active":true,"year":"2022","xqbsm":"L000000500001","schoolName":"浙大城市学院附属学校","lng":"120.16388465605296","lat":"30.31576689715593","sequence":6,"bak1":null,"bak2":null,"bak3":null,"bak4":null,"bak5":null},{"id":22525,"createTime":"2022-06-23 15:24:53","updateTime":"2022-06-23 15:12:55","createUser":"gsqjyj","updateUser":null,"active":true,"year":"2022","xqbsm":"L000000500001","schoolName":"浙大城市学院附属学校","lng":"120.16192635004127","lat":"30.31748156699823","sequence":7,"bak1":null,"bak2":null,"bak3":null,"bak4":null,"bak5":null},{"id":22526,"createTime":"2022-06-23 15:24:53","updateTime":"2022-06-23 15:12:55","createUser":"gsqjyj","updateUser":null,"active":true,"year":"2022","xqbsm":"L000000500001","schoolName":"浙大城市学院附属学校","lng":"120.15923143351134","lat":"30.31888446348389","sequence":8,"bak1":null,"bak2":null,"bak3":null,"bak4":null,"bak5":null},{"id":22527,"createTime":"2022-06-23 15:24:53","updateTime":"2022-06-23 15:12:55","createUser":"gsqjyj","updateUser":null,"active":true,"year":"2022","xqbsm":"L000000500001","schoolName":"浙大城市学院附属学校","lng":"120.15362600712908","lat":"30.31953914156683","sequence":9,"bak1":null,"bak2":null,"bak3":null,"bak4":null,"bak5":null},{"id":22528,"createTime":"2022-06-23 15:24:53","updateTime":"2022-06-23 15:12:55","createUser":"gsqjyj","updateUser":null,"active":true,"year":"2022","xqbsm":"L000000500001","schoolName":"浙大城市学院附属学校","lng":"120.15294329494142","lat":"30.325633679680383","sequence":10,"bak1":null,"bak2":null,"bak3":null,"bak4":null,"bak5":null}]}}